Workbook

Sheet Instrucciones
B2: Casos de prueba de Quanela
B3: 307 casos · versión del 7 de octubre de 2026 · basados en el código, la base de datos y el Centro de ayuda
B5: Para qué sirve | C5: Probar a mano todas las funciones de la app: lo que debe funcionar, los errores esperados, los permisos de cada rol y la seguridad entre negocios.
B6: Cómo usarlo | C6: 1. En «Casos de prueba», filtra por módulo, prioridad o rol. 2. Sigue las precondiciones y los pasos. 3. Compara con el resultado esperado. 4. Llena «Estado», «Resultado obtenido», «Ejecutado por» y «Fecha». 5. Si falla, anota el ticket o la descripción en «Defecto / ticket». La hoja «Resumen» se actualiza sola con los estados.
B7: Estados | C7: Pendiente · Pasó · Falló · Bloqueado (no se pudo ejecutar por otra falla o por falta de datos) · No aplica.
B8: Prioridad | C8: Alta: dinero, inventario, permisos, seguridad o flujo principal. Media: funciones secundarias o mensajes. Baja: detalles visuales o de texto.
B9: Tipos | C9: Funcional (camino feliz) · Negativo · Validación · Permisos · Seguridad · Integración (un módulo afecta a otro) · UI/UX · Accesibilidad · Regresión (un error ya corregido no debe volver) · Rendimiento.
B10: Ambiente | C10: Usa una cuenta de prueba, nunca un negocio real. Para Permisos necesitas un usuario por rol: ADMIN, GERENTE, CAJA, COCINA, INVENTARIO y DOMICILIARIO. Para Seguridad, un segundo negocio de prueba.
B11: Datos de prueba | C11: Solo datos ficticios (por ejemplo «Laura Gómez», laura@negocio.co, +57 300 123 4567). No uses teléfonos, correos ni nombres de clientes reales.
B12: Casos con «anotar como defecto» | C12: En unos casos el resultado esperado avisa que, leyendo el código, parece haber un error. El resultado esperado describe cómo debería funcionar; si la app hace otra cosa, márcalo «Falló».
B13: Posibles defectos | C13: La hoja «Posibles defectos» lista lo que se encontró al revisar el código. No se reprodujo en la app: confírmalo con los casos relacionados.
B14: Referencia | C14: La columna «Referencia» indica el archivo, la ADR o el artículo de ayuda que respalda cada caso.

Sheet Resumen
A1: Resumen por módulo
A3: Módulo | B3: Casos | C3: Alta | D3: Media | E3: Baja | F3: Pendiente | G3: Pasó | H3: Falló | I3: Bloqueado | J3: No aplica | K3: % ejecutado | L3: % aprobado
A4: Landing y documentación | B4: =COUNTIF('Casos de prueba'!$B:$B,$A4) | C4: =COUNTIFS('Casos de prueba'!$B:$B,$A4,'Casos de prueba'!$F:$F,"Alta") | D4: =COUNTIFS('Casos de prueba'!$B:$B,$A4,'Casos de prueba'!$F:$F,"Media") | E4: =COUNTIFS('Casos de prueba'!$B:$B,$A4,'Casos de prueba'!$F:$F,"Baja") | F4: =COUNTIFS('Casos de prueba'!$B:$B,$A4,'Casos de prueba'!$L:$L,"Pendiente") | G4: =COUNTIFS('Casos de prueba'!$B:$B,$A4,'Casos de prueba'!$L:$L,"Pasó") | H4: =COUNTIFS('Casos de prueba'!$B:$B,$A4,'Casos de prueba'!$L:$L,"Falló") | I4: =COUNTIFS('Casos de prueba'!$B:$B,$A4,'Casos de prueba'!$L:$L,"Bloqueado") | J4: =COUNTIFS('Casos de prueba'!$B:$B,$A4,'Casos de prueba'!$L:$L,"No aplica") | K4: =IF(B4-J4=0,0,(G4+H4+I4)/(B4-J4)) | L4: =IF(G4+H4=0,0,G4/(G4+H4))
A5: Acceso y cuenta | B5: =COUNTIF('Casos de prueba'!$B:$B,$A5) | C5: =COUNTIFS('Casos de prueba'!$B:$B,$A5,'Casos de prueba'!$F:$F,"Alta") | D5: =COUNTIFS('Casos de prueba'!$B:$B,$A5,'Casos de prueba'!$F:$F,"Media") | E5: =COUNTIFS('Casos de prueba'!$B:$B,$A5,'Casos de prueba'!$F:$F,"Baja") | F5: =COUNTIFS('Casos de prueba'!$B:$B,$A5,'Casos de prueba'!$L:$L,"Pendiente") | G5: =COUNTIFS('Casos de prueba'!$B:$B,$A5,'Casos de prueba'!$L:$L,"Pasó") | H5: =COUNTIFS('Casos de prueba'!$B:$B,$A5,'Casos de prueba'!$L:$L,"Falló") | I5: =COUNTIFS('Casos de prueba'!$B:$B,$A5,'Casos de prueba'!$L:$L,"Bloqueado") | J5: =COUNTIFS('Casos de prueba'!$B:$B,$A5,'Casos de prueba'!$L:$L,"No aplica") | K5: =IF(B5-J5=0,0,(G5+H5+I5)/(B5-J5)) | L5: =IF(G5+H5=0,0,G5/(G5+H5))
A6: Equipo | B6: =COUNTIF('Casos de prueba'!$B:$B,$A6) | C6: =COUNTIFS('Casos de prueba'!$B:$B,$A6,'Casos de prueba'!$F:$F,"Alta") | D6: =COUNTIFS('Casos de prueba'!$B:$B,$A6,'Casos de prueba'!$F:$F,"Media") | E6: =COUNTIFS('Casos de prueba'!$B:$B,$A6,'Casos de prueba'!$F:$F,"Baja") | F6: =COUNTIFS('Casos de prueba'!$B:$B,$A6,'Casos de prueba'!$L:$L,"Pendiente") | G6: =COUNTIFS('Casos de prueba'!$B:$B,$A6,'Casos de prueba'!$L:$L,"Pasó") | H6: =COUNTIFS('Casos de prueba'!$B:$B,$A6,'Casos de prueba'!$L:$L,"Falló") | I6: =COUNTIFS('Casos de prueba'!$B:$B,$A6,'Casos de prueba'!$L:$L,"Bloqueado") | J6: =COUNTIFS('Casos de prueba'!$B:$B,$A6,'Casos de prueba'!$L:$L,"No aplica") | K6: =IF(B6-J6=0,0,(G6+H6+I6)/(B6-J6)) | L6: =IF(G6+H6=0,0,G6/(G6+H6))
A7: Configuración | B7: =COUNTIF('Casos de prueba'!$B:$B,$A7) | C7: =COUNTIFS('Casos de prueba'!$B:$B,$A7,'Casos de prueba'!$F:$F,"Alta") | D7: =COUNTIFS('Casos de prueba'!$B:$B,$A7,'Casos de prueba'!$F:$F,"Media") | E7: =COUNTIFS('Casos de prueba'!$B:$B,$A7,'Casos de prueba'!$F:$F,"Baja") | F7: =COUNTIFS('Casos de prueba'!$B:$B,$A7,'Casos de prueba'!$L:$L,"Pendiente") | G7: =COUNTIFS('Casos de prueba'!$B:$B,$A7,'Casos de prueba'!$L:$L,"Pasó") | H7: =COUNTIFS('Casos de prueba'!$B:$B,$A7,'Casos de prueba'!$L:$L,"Falló") | I7: =COUNTIFS('Casos de prueba'!$B:$B,$A7,'Casos de prueba'!$L:$L,"Bloqueado") | J7: =COUNTIFS('Casos de prueba'!$B:$B,$A7,'Casos de prueba'!$L:$L,"No aplica") | K7: =IF(B7-J7=0,0,(G7+H7+I7)/(B7-J7)) | L7: =IF(G7+H7=0,0,G7/(G7+H7))
A8: Roles y seguridad | B8: =COUNTIF('Casos de prueba'!$B:$B,$A8) | C8: =COUNTIFS('Casos de prueba'!$B:$B,$A8,'Casos de prueba'!$F:$F,"Alta") | D8: =COUNTIFS('Casos de prueba'!$B:$B,$A8,'Casos de prueba'!$F:$F,"Media") | E8: =COUNTIFS('Casos de prueba'!$B:$B,$A8,'Casos de prueba'!$F:$F,"Baja") | F8: =COUNTIFS('Casos de prueba'!$B:$B,$A8,'Casos de prueba'!$L:$L,"Pendiente") | G8: =COUNTIFS('Casos de prueba'!$B:$B,$A8,'Casos de prueba'!$L:$L,"Pasó") | H8: =COUNTIFS('Casos de prueba'!$B:$B,$A8,'Casos de prueba'!$L:$L,"Falló") | I8: =COUNTIFS('Casos de prueba'!$B:$B,$A8,'Casos de prueba'!$L:$L,"Bloqueado") | J8: =COUNTIFS('Casos de prueba'!$B:$B,$A8,'Casos de prueba'!$L:$L,"No aplica") | K8: =IF(B8-J8=0,0,(G8+H8+I8)/(B8-J8)) | L8: =IF(G8+H8=0,0,G8/(G8+H8))
A9: Portal de administración | B9: =COUNTIF('Casos de prueba'!$B:$B,$A9) | C9: =COUNTIFS('Casos de prueba'!$B:$B,$A9,'Casos de prueba'!$F:$F,"Alta") | D9: =COUNTIFS('Casos de prueba'!$B:$B,$A9,'Casos de prueba'!$F:$F,"Media") | E9: =COUNTIFS('Casos de prueba'!$B:$B,$A9,'Casos de prueba'!$F:$F,"Baja") | F9: =COUNTIFS('Casos de prueba'!$B:$B,$A9,'Casos de prueba'!$L:$L,"Pendiente") | G9: =COUNTIFS('Casos de prueba'!$B:$B,$A9,'Casos de prueba'!$L:$L,"Pasó") | H9: =COUNTIFS('Casos de prueba'!$B:$B,$A9,'Casos de prueba'!$L:$L,"Falló") | I9: =COUNTIFS('Casos de prueba'!$B:$B,$A9,'Casos de prueba'!$L:$L,"Bloqueado") | J9: =COUNTIFS('Casos de prueba'!$B:$B,$A9,'Casos de prueba'!$L:$L,"No aplica") | K9: =IF(B9-J9=0,0,(G9+H9+I9)/(B9-J9)) | L9: =IF(G9+H9=0,0,G9/(G9+H9))
A10: Inicio | B10: =COUNTIF('Casos de prueba'!$B:$B,$A10) | C10: =COUNTIFS('Casos de prueba'!$B:$B,$A10,'Casos de prueba'!$F:$F,"Alta") | D10: =COUNTIFS('Casos de prueba'!$B:$B,$A10,'Casos de prueba'!$F:$F,"Media") | E10: =COUNTIFS('Casos de prueba'!$B:$B,$A10,'Casos de prueba'!$F:$F,"Baja") | F10: =COUNTIFS('Casos de prueba'!$B:$B,$A10,'Casos de prueba'!$L:$L,"Pendiente") | G10: =COUNTIFS('Casos de prueba'!$B:$B,$A10,'Casos de prueba'!$L:$L,"Pasó") | H10: =COUNTIFS('Casos de prueba'!$B:$B,$A10,'Casos de prueba'!$L:$L,"Falló") | I10: =COUNTIFS('Casos de prueba'!$B:$B,$A10,'Casos de prueba'!$L:$L,"Bloqueado") | J10: =COUNTIFS('Casos de prueba'!$B:$B,$A10,'Casos de prueba'!$L:$L,"No aplica") | K10: =IF(B10-J10=0,0,(G10+H10+I10)/(B10-J10)) | L10: =IF(G10+H10=0,0,G10/(G10+H10))
A11: Notificaciones | B11: =COUNTIF('Casos de prueba'!$B:$B,$A11) | C11: =COUNTIFS('Casos de prueba'!$B:$B,$A11,'Casos de prueba'!$F:$F,"Alta") | D11: =COUNTIFS('Casos de prueba'!$B:$B,$A11,'Casos de prueba'!$F:$F,"Media") | E11: =COUNTIFS('Casos de prueba'!$B:$B,$A11,'Casos de prueba'!$F:$F,"Baja") | F11: =COUNTIFS('Casos de prueba'!$B:$B,$A11,'Casos de prueba'!$L:$L,"Pendiente") | G11: =COUNTIFS('Casos de prueba'!$B:$B,$A11,'Casos de prueba'!$L:$L,"Pasó") | H11: =COUNTIFS('Casos de prueba'!$B:$B,$A11,'Casos de prueba'!$L:$L,"Falló") | I11: =COUNTIFS('Casos de prueba'!$B:$B,$A11,'Casos de prueba'!$L:$L,"Bloqueado") | J11: =COUNTIFS('Casos de prueba'!$B:$B,$A11,'Casos de prueba'!$L:$L,"No aplica") | K11: =IF(B11-J11=0,0,(G11+H11+I11)/(B11-J11)) | L11: =IF(G11+H11=0,0,G11/(G11+H11))
A12: Pedidos | B12: =COUNTIF('Casos de prueba'!$B:$B,$A12) | C12: =COUNTIFS('Casos de prueba'!$B:$B,$A12,'Casos de prueba'!$F:$F,"Alta") | D12: =COUNTIFS('Casos de prueba'!$B:$B,$A12,'Casos de prueba'!$F:$F,"Media") | E12: =COUNTIFS('Casos de prueba'!$B:$B,$A12,'Casos de prueba'!$F:$F,"Baja") | F12: =COUNTIFS('Casos de prueba'!$B:$B,$A12,'Casos de prueba'!$L:$L,"Pendiente") | G12: =COUNTIFS('Casos de prueba'!$B:$B,$A12,'Casos de prueba'!$L:$L,"Pasó") | H12: =COUNTIFS('Casos de prueba'!$B:$B,$A12,'Casos de prueba'!$L:$L,"Falló") | I12: =COUNTIFS('Casos de prueba'!$B:$B,$A12,'Casos de prueba'!$L:$L,"Bloqueado") | J12: =COUNTIFS('Casos de prueba'!$B:$B,$A12,'Casos de prueba'!$L:$L,"No aplica") | K12: =IF(B12-J12=0,0,(G12+H12+I12)/(B12-J12)) | L12: =IF(G12+H12=0,0,G12/(G12+H12))
A13: Operación y despacho | B13: =COUNTIF('Casos de prueba'!$B:$B,$A13) | C13: =COUNTIFS('Casos de prueba'!$B:$B,$A13,'Casos de prueba'!$F:$F,"Alta") | D13: =COUNTIFS('Casos de prueba'!$B:$B,$A13,'Casos de prueba'!$F:$F,"Media") | E13: =COUNTIFS('Casos de prueba'!$B:$B,$A13,'Casos de prueba'!$F:$F,"Baja") | F13: =COUNTIFS('Casos de prueba'!$B:$B,$A13,'Casos de prueba'!$L:$L,"Pendiente") | G13: =COUNTIFS('Casos de prueba'!$B:$B,$A13,'Casos de prueba'!$L:$L,"Pasó") | H13: =COUNTIFS('Casos de prueba'!$B:$B,$A13,'Casos de prueba'!$L:$L,"Falló") | I13: =COUNTIFS('Casos de prueba'!$B:$B,$A13,'Casos de prueba'!$L:$L,"Bloqueado") | J13: =COUNTIFS('Casos de prueba'!$B:$B,$A13,'Casos de prueba'!$L:$L,"No aplica") | K13: =IF(B13-J13=0,0,(G13+H13+I13)/(B13-J13)) | L13: =IF(G13+H13=0,0,G13/(G13+H13))
A14: Pagos y cartera | B14: =COUNTIF('Casos de prueba'!$B:$B,$A14) | C14: =COUNTIFS('Casos de prueba'!$B:$B,$A14,'Casos de prueba'!$F:$F,"Alta") | D14: =COUNTIFS('Casos de prueba'!$B:$B,$A14,'Casos de prueba'!$F:$F,"Media") | E14: =COUNTIFS('Casos de prueba'!$B:$B,$A14,'Casos de prueba'!$F:$F,"Baja") | F14: =COUNTIFS('Casos de prueba'!$B:$B,$A14,'Casos de prueba'!$L:$L,"Pendiente") | G14: =COUNTIFS('Casos de prueba'!$B:$B,$A14,'Casos de prueba'!$L:$L,"Pasó") | H14: =COUNTIFS('Casos de prueba'!$B:$B,$A14,'Casos de prueba'!$L:$L,"Falló") | I14: =COUNTIFS('Casos de prueba'!$B:$B,$A14,'Casos de prueba'!$L:$L,"Bloqueado") | J14: =COUNTIFS('Casos de prueba'!$B:$B,$A14,'Casos de prueba'!$L:$L,"No aplica") | K14: =IF(B14-J14=0,0,(G14+H14+I14)/(B14-J14)) | L14: =IF(G14+H14=0,0,G14/(G14+H14))
A15: Clientes | B15: =COUNTIF('Casos de prueba'!$B:$B,$A15) | C15: =COUNTIFS('Casos de prueba'!$B:$B,$A15,'Casos de prueba'!$F:$F,"Alta") | D15: =COUNTIFS('Casos de prueba'!$B:$B,$A15,'Casos de prueba'!$F:$F,"Media") | E15: =COUNTIFS('Casos de prueba'!$B:$B,$A15,'Casos de prueba'!$F:$F,"Baja") | F15: =COUNTIFS('Casos de prueba'!$B:$B,$A15,'Casos de prueba'!$L:$L,"Pendiente") | G15: =COUNTIFS('Casos de prueba'!$B:$B,$A15,'Casos de prueba'!$L:$L,"Pasó") | H15: =COUNTIFS('Casos de prueba'!$B:$B,$A15,'Casos de prueba'!$L:$L,"Falló") | I15: =COUNTIFS('Casos de prueba'!$B:$B,$A15,'Casos de prueba'!$L:$L,"Bloqueado") | J15: =COUNTIFS('Casos de prueba'!$B:$B,$A15,'Casos de prueba'!$L:$L,"No aplica") | K15: =IF(B15-J15=0,0,(G15+H15+I15)/(B15-J15)) | L15: =IF(G15+H15=0,0,G15/(G15+H15))
... A24: Transversal | B24: =COUNTIF('Casos de prueba'!$B:$B,$A24) | C24: =COUNTIFS('Casos de prueba'!$B:$B,$A24,'Casos de prueba'!$F:$F,"Alta") | D24: =COUNTIFS('Casos de prueba'!$B:$B,$A24,'Casos de prueba'!$F:$F,"Media") | E24: =COUNTIFS('Casos de prueba'!$B:$B,$A24,'Casos de prueba'!$F:$F,"Baja") | F24: =COUNTIFS('Casos de prueba'!$B:$B,$A24,'Casos de prueba'!$L:$L,"Pendiente") | G24: =COUNTIFS('Casos de prueba'!$B:$B,$A24,'Casos de prueba'!$L:$L,"Pasó") | H24: =COUNTIFS('Casos de prueba'!$B:$B,$A24,'Casos de prueba'!$L:$L,"Falló") | I24: =COUNTIFS('Casos de prueba'!$B:$B,$A24,'Casos de prueba'!$L:$L,"Bloqueado") | J24: =COUNTIFS('Casos de prueba'!$B:$B,$A24,'Casos de prueba'!$L:$L,"No aplica") | K24: =IF(B24-J24=0,0,(G24+H24+I24)/(B24-J24)) | L24: =IF(G24+H24=0,0,G24/(G24+H24))
A25: Total | B25: =SUM(B4:B24) | C25: =SUM(C4:C24) | D25: =SUM(D4:D24) | E25: =SUM(E4:E24) | F25: =SUM(F4:F24) | G25: =SUM(G4:G24) | H25: =SUM(H4:H24) | I25: =SUM(I4:I24) | J25: =SUM(J4:J24) | K25: =IF(B25-J25=0,0,(G25+H25+I25)/(B25-J25)) | L25: =IF(G25+H25=0,0,G25/(G25+H25))
A28: Casos por tipo
A29: Tipo | B29: Casos
A30: Funcional | B30: =COUNTIF('Casos de prueba'!$E:$E,$A30)
A31: Negativo | B31: =COUNTIF('Casos de prueba'!$E:$E,$A31)
A32: Validación | B32: =COUNTIF('Casos de prueba'!$E:$E,$A32)
A33: Permisos | B33: =COUNTIF('Casos de prueba'!$E:$E,$A33)
A34: Seguridad | B34: =COUNTIF('Casos de prueba'!$E:$E,$A34)
A35: Integración | B35: =COUNTIF('Casos de prueba'!$E:$E,$A35)
A36: UI/UX | B36: =COUNTIF('Casos de prueba'!$E:$E,$A36)
A37: Accesibilidad | B37: =COUNTIF('Casos de prueba'!$E:$E,$A37)
A38: Regresión | B38: =COUNTIF('Casos de prueba'!$E:$E,$A38)
A39: Rendimiento | B39: =COUNTIF('Casos de prueba'!$E:$E,$A39)

Sheet Casos de prueba
A1: ID | B1: Módulo | C1: Funcionalidad | D1: Título | E1: Tipo | F1: Prioridad | G1: Rol | H1: Precondiciones | I1: Pasos | J1: Datos de prueba | K1: Resultado esperado | L1: Estado | M1: Resultado obtenido | N1: Ejecutado por | O1: Fecha | P1: Defecto / ticket | Q1: Referencia
A2: LND-001 | B2: Landing y documentación | C2: Landing | D2: La landing en quanela.com sin sesión muestra navegación y llamados a la acción | E2: Funcional | F2: Media | G2: Sin sesión | H2: Navegador sin sesión de Quanela (cookies de .quanela.com borradas). | I2: 1. Abrir https://quanela.com/ 2. Revisar la barra superior 3. Pulsar «Iniciar sesión» 4. Volver y pulsar «Crear cuenta» | K2: Se ve la landing con los enlaces «Producto», «Funcionalidades», «Precios», «FAQ» y «Ayuda». «Iniciar sesión» lleva a /login y «Crear cuenta» lleva a /registro. | L2: Pendiente | Q2: src/modules/landing/components/LandingNav.tsx; ADR 0036
A3: LND-002 | B3: Landing y documentación | C3: Landing con sesión | D3: quanela.com/ sigue mostrando la landing con sesión abierta y ofrece «Ir a mi cuenta» | E3: Regresión | F3: Alta | G3: ADMIN | H3: Sesión abierta como ADMIN de un negocio con subdominio (p. ej. fr3rk6.quanela.com). | I3: 1. Con la sesión abierta, abrir https://quanela.com/ 2. Comprobar que no hay redirección automática al negocio 3. Pulsar «Ir a mi cuenta» en la barra superior | J3: Usuario: laura@negocio.co | K3: quanela.com/ muestra la landing (no redirige al subdominio). La barra muestra «Ir a mi cuenta» en vez de «Iniciar sesión»/«Crear cuenta». Al pulsarlo va a /app y de ahí a la cuenta por defecto en su subdominio ({código}.quanela.com/k/{cuenta}/…). | L3: Pendiente | Q3: ADR 0036; src/app/routes.tsx; src/modules/landing/components/LandingNav.tsx
A4: LND-003 | B4: Landing y documentación | C4: Precios | D4: El botón de cada plan lleva al registro con el plan elegido, o a mi cuenta si ya hay sesión | E4: Funcional | F4: Media | G4: Sin sesión / ADMIN | H4: Planes públicos cargados en la sección «Precios» de la landing. | I4: 1. Sin sesión, ir a la sección «Precios» de la landing 2. Alternar «Mensual» / «Anual» 3. Pulsar el botón de un plan de autoservicio 4. Iniciar sesión, volver a la landing y revisar el mismo botón | K4: Sin sesión, el botón del plan lleva a /registro?plan={clave} y el registro muestra ese plan elegido. Un plan de ventas abre su enlace de contacto. Con sesión, el botón dice «Ir a mi cuenta» y lleva a /app (una organización por persona). | L4: Pendiente | Q4: src/modules/landing/components/PricingSection.tsx; src/shared/plans/plans.ts; ADR 0010
A5: LND-004 | B5: Landing y documentación | C5: Documentación en doc.quanela.com | D5: La ayuda abre en doc.quanela.com sin sesión y «Entrar» lleva al login | E5: Integración | F5: Media | G5: Sin sesión | H5: Sin sesión. Dominio raíz configurado (quanela.com). | I5: 1. En la landing pulsar «Ayuda» (barra superior) 2. Abrir el artículo «Preguntas frecuentes» 3. Pulsar «Entrar» en la cabecera de la documentación | K5: «Ayuda» abre https://doc.quanela.com/ sin pedir sesión ni resolver negocio. Los artículos cargan sin el prefijo /help (p. ej. doc.quanela.com/faq/faq). «Entrar» lleva a https://quanela.com/login. | L5: Pendiente | Q5: ADR 0035; src/modules/help/HelpLayout.tsx; src/modules/help/lib.ts
A6: LND-005 | B6: Landing y documentación | C6: Landing en el celular | D6: El menú móvil de la landing abre y cierra con su botón accesible | E6: Accesibilidad | F6: Baja | G6: Sin sesión | H6: Ventana de 375 px de ancho (celular). | I6: 1. Abrir quanela.com 2. Pulsar el botón de menú (aria-label «Abrir menú») 3. Navegar con Tab por los enlaces 4. Pulsar el mismo botón (ahora «Cerrar menú») | K6: El menú muestra las secciones, «Ayuda», «Iniciar sesión» y «Crear cuenta». La etiqueta accesible cambia entre «Abrir menú» y «Cerrar menú». La página no tiene desplazamiento horizontal. | L6: Pendiente | Q6: src/modules/landing/components/LandingNav.tsx
A7: ACC-001 | B7: Acceso y cuenta | C7: Subdominio del negocio | D7: El subdominio con código válido muestra el login del negocio con su nombre y dirección | E7: Funcional | F7: Alta | G7: Sin sesión | H7: Negocio «Brasa del Barrio» activo con código A7K92P. | I7: 1. Abrir https://a7k92p.quanela.com/ 2. Revisar el subtítulo del login | J7: Código: A7K92P | K7: Se muestra el login «Inicia sesión» con el texto «Entra a Brasa del Barrio en a7k92p.quanela.com.» y el enlace «Ir a Quanela» hacia quanela.com. | L7: Pendiente | Q7: ADR 0021; ADR 0022; src/modules/auth/pages/LoginPage.tsx
A8: ACC-002 | B8: Acceso y cuenta | C8: Subdominio del negocio | D8: Un subdominio con el nombre del negocio o un código inexistente muestra «Esta dirección no existe» | E8: Negativo | F8: Alta | G8: Sin sesión | H8: Existe el negocio «Brasa del Barrio» (slug brasa-del-barrio, código A7K92P). | I8: 1. Abrir https://brasa-del-barrio.quanela.com/ 2. Abrir https://zz99zz.quanela.com/ 3. Pulsar «Ir a Quanela» | J8: Subdominios: brasa-del-barrio, zz99zz | K8: En ambos casos aparece «Esta dirección no existe» con el texto «No hay ningún espacio de Quanela en {dirección}. Revisa que la dirección esté bien escrita.». El nombre no sirve como respaldo. «Ir a Quanela» lleva a quanela.com. | L8: Pendiente | Q8: ADR 0022 (3.2, 3.4); src/shared/tenant/TenantProvider.tsx; supabase/tests/tenants.sql
A9: ACC-003 | B9: Acceso y cuenta | C9: Subdominio del negocio | D9: Un negocio desactivado no deja entrar a nadie | E9: Negativo | F9: Alta | G9: Sin sesión / ADMIN | H9: El Global Admin desactivó el negocio «Brasa del Barrio» (A7K92P). | I9: 1. Abrir https://a7k92p.quanela.com/ 2. Intentar iniciar sesión con un usuario del negocio | J9: Usuario: laura@negocio.co | K9: Aparece «Brasa del Barrio está desactivado» con «Por ahora nadie puede entrar. Si crees que es un error, contacta a quien administra tu negocio.» y el enlace «Ir a Quanela». | L9: Pendiente | Q9: src/shared/tenant/TenantProvider.tsx; ADR 0021 (2.2)
A10: ACC-004 | B10: Acceso y cuenta | C10: Aislamiento por subdominio | D10: Un usuario del negocio A que abre el subdominio del negocio B ve «No tienes acceso» | E10: Seguridad | F10: Alta | G10: ADMIN (negocio A) | H10: Laura es ADMIN solo en el negocio A (código A7K92P). El negocio B tiene código Q3W8RT. | I10: 1. Iniciar sesión en a7k92p.quanela.com 2. Abrir https://q3w8rt.quanela.com/k/{cuenta-de-B}/customers 3. Revisar la pantalla | J10: Usuario: laura@negocio.co | K10: Aparece «No tienes acceso a {Negocio B}» con «Tu usuario no pertenece a este espacio...». Bajo «Tus espacios:» se lista solo el negocio A con su código. Está el botón «Entrar con otro usuario». No se ve ningún dato de B. | L10: Pendiente | Q10: src/shared/tenant/TenantProvider.tsx; supabase/tests/tenants.sql ('Knowing the code of B gives nothing')
A11: ACC-005 | B11: Acceso y cuenta | C11: Sesión compartida | D11: Con un solo inicio de sesión se entra a los dos negocios, y cerrar sesión cierra en todos los subdominios | E11: Integración | F11: Media | G11: CAJA en A / COCINA en B | H11: Andrés es CAJA en el negocio A y COCINA en el negocio B. | I11: 1. Iniciar sesión en el subdominio de A 2. En «Tus cuentas», elegir la cuenta del negocio B 3. Comprobar que no se pide el login otra vez 4. Pulsar «Cerrar sesión» en el menú de usuario 5. Volver al subdominio de A | J11: Usuario: andres@negocio.co | K11: Al elegir la cuenta de B se abre su subdominio con la sesión activa y el rol COCINA. Tras «Cerrar sesión», los dos subdominios muestran su login. | L11: Pendiente | Q11: ADR 0021 (2.3); ADR 0024 (menú de usuario); supabase/tests/tenants.sql ('Membership')
A12: ACC-006 | B12: Acceso y cuenta | C12: Inicio de sesión | D12: Un usuario con correo y contraseña válidos entra a su cuenta y a la pantalla de su rol | E12: Funcional | F12: Alta | G12: CAJA | H12: Usuario activo con rol CAJA en una sola cuenta. | I12: 1. Abrir el subdominio del negocio 2. Escribir el correo en «Correo electrónico» 3. Escribir la contraseña en «Contraseña» 4. Pulsar «Iniciar sesión» | J12: Correo: camila.caja@negocio.co; contraseña de prueba de 8+ caracteres | K12: Entra directo a la cuenta y aterriza en Operación → Tablero (inicio del rol CAJA). Arriba se ve el indicador «Cuenta · CAJA». | L12: Pendiente | Q12: content/help/getting-started/switch-account.md; src/app/navigation.ts (homeSection)
A13: ACC-007 | B13: Acceso y cuenta | C13: Inicio de sesión | D13: Una contraseña incorrecta no inicia sesión y muestra el error en español bajo «Contraseña» | E13: Negativo | F13: Alta | G13: Sin sesión | H13: Usuario activo existente. | I13: 1. Abrir /login 2. Escribir un correo válido 3. Escribir una contraseña equivocada 4. Pulsar «Iniciar sesión» | J13: Correo: laura@negocio.co; contraseña: Clave-Erronea-1 | K13: No se inicia sesión. Aparece un error bajo el campo «Contraseña», en español (p. ej. «Correo o contraseña incorrectos.», como en el portal admin). HALLAZGO: hoy el login de la app muestra el texto de Supabase sin traducir («Invalid login credentials»). | L13: Pendiente | Q13: src/modules/auth/pages/LoginPage.tsx; src/shared/hooks/useAuth.tsx (signIn); admin/src/auth/LoginPage.tsx
A14: ACC-008 | B14: Acceso y cuenta | C14: Inicio de sesión | D14: El parámetro ?next= solo admite rutas internas (no redirige a otro sitio) | E14: Seguridad | F14: Alta | G14: Sin sesión | H14: Usuario activo. | I14: 1. Abrir /login?next=https://sitio-externo.example/robo 2. Iniciar sesión 3. Repetir con /login?next=//sitio-externo.example 4. Repetir con /login?next=/k/{cuenta}/customers | J14: Correo: laura@negocio.co | K14: Con las dos primeras direcciones, después de iniciar sesión se va a /app (la cuenta por defecto), nunca al sitio externo. Con la ruta interna se abre /k/{cuenta}/customers. | L14: Pendiente | Q14: src/modules/auth/pages/LoginPage.tsx (target = next interno o APP_ENTRY)
A15: ACC-009 | B15: Acceso y cuenta | C15: Métodos del dueño (Google/Instagram/teléfono) | D15: Un usuario invitado que entra con Google es devuelto al login con un aviso | E15: Seguridad | F15: Alta | G15: COCINA (invitado) | H15: Sofía fue invitada como COCINA y activó su usuario con correo y contraseña. No es dueña de ningún negocio. Google está activo como método. | I15: 1. En /login, bajo «¿Creaste tu negocio con Google, ...?», pulsar «Continuar con Google» 2. Completar el inicio de sesión con su cuenta de Google del mismo correo 3. Observar a dónde vuelve | J15: Correo: sofia.cocina@negocio.co | K15: Se cierra la sesión y vuelve a /login con el aviso «Esa forma de entrar es para quien creó su negocio en Quanela. Entra con tu correo y tu contraseña.». No entra a la app. | L15: Pendiente | Q15: src/modules/signup/ownerSession.ts (NOT_AN_OWNER_NOTICE); src/modules/signup/pages/SignUpPage.tsx; ADR 0025 (D3)
A16: ACC-010 | B16: Acceso y cuenta | C16: Usuario desactivado | D16: Un usuario desactivado que inicia sesión ve «Usuario desactivado» y solo puede cerrar sesión | E16: Seguridad | F16: Alta | G16: CAJA (desactivado) | H16: Un ADMIN desactivó a Camila desde Usuarios. | I16: 1. Iniciar sesión con el usuario de Camila 2. Intentar abrir /k/{cuenta}/operations | J16: Correo: camila.caja@negocio.co | K16: Aparece «Usuario desactivado» con «{nombre}, tu usuario está desactivado en Quanela. Si crees que es un error, contacta al administrador de tu negocio.» y el botón «Cerrar sesión». No se puede abrir ninguna ruta de la cuenta. | L16: Pendiente | Q16: src/modules/auth/pages/AccountDisabledPage.tsx; src/app/ProtectedRoute.tsx
A17: ACC-011 | B17: Acceso y cuenta | C17: Acceso sin sesión | D17: Una ruta protegida abierta sin sesión lleva al login | E17: Seguridad | F17: Alta | G17: Sin sesión | H17: Sin sesión en el navegador. | I17: 1. Abrir directamente https://{código}.quanela.com/k/{cuenta}/users 2. Abrir /k/{cuenta}/settings/general 3. Abrir /cuentas | K17: En todos los casos se redirige a /login y no se carga ningún dato de la cuenta. Nota: el login no recuerda la ruta pedida (no agrega ?next=), así que después de entrar se va a /app. | L17: Pendiente | Q17: src/app/ProtectedRoute.tsx; src/app/routes.tsx
A18: ACC-012 | B18: Acceso y cuenta | C18: Registro del dueño | D18: Crear un negocio con correo de principio a fin | E18: Funcional | F18: Alta | G18: Sin sesión (dueño nuevo) | H18: Registro público activo. El correo no existe en Quanela. | I18: 1. Abrir quanela.com/registro 2. Paso 1 de 3: pulsar «Continuar con email», escribir «Tu nombre», «Correo» y «Contraseña», y pulsar «Continuar» 3. Paso 2 de 3: pulsar «Elegir» en un plan 4. Paso 3 de 3: completar «Nombre del negocio», «Sector», «Categoría», «Ciudad» y «País», y dejar vacío «Nombre de la cuenta» 5. Pulsar «Crear mi negocio» 6. Abrir el enlace del correo de confirmación 7. Pulsar «Entrar a mi espacio» | J18: Laura Gómez; laura@negocio.co; Hamburguesas La Esquina; Comida rápida / Hamburguesas; Bogotá; Colombia | K18: Tras «Crear mi negocio» aparece «Revisa tu correo». Al confirmar se ve «Tu cuenta ha sido creada» con «Código: XXXXXX» (6 caracteres, mayúsculas) y «Tu espacio Quanela: xxxxxx.quanela.com», con botón para copiar la dirección. «Entrar a mi espacio» abre la cuenta «Hamburguesas La Esquina» (toma el nombre del negocio) con la tarjeta de bienvenida y sus atajos. Laura queda como SUPER_ADMIN y ADMIN de la primera cuenta. | L18: Pendiente | Q18: content/help/getting-started/create-business.md; src/modules/signup/pages/SignUpPage.tsx; src/modules/signup/pages/SignUpConfirmedPage.tsx; supabase/tests/signup.sql; supabase/tests/plans.sql
A19: ACC-013 | B19: Acceso y cuenta | C19: Registro del dueño | D19: Validaciones del paso «Crea tu usuario» | E19: Validación | F19: Alta | G19: Sin sesión | H19: En /registro, «Continuar con email». | I19: 1. Escribir «L» en «Tu nombre» 2. Escribir «laura.negocio.co» en «Correo» 3. Cambiarlo a «laura@negocio» 4. Escribir «1234567» en «Contraseña» 5. Corregir todos los campos | J19: Nombre: L; correos: laura.negocio.co / laura@negocio; contraseña: 1234567 | K19: Errores en orden: «Mínimo 2 caracteres» (nombre), «Falta la @ del correo.», «Falta el dominio del correo (por ejemplo, @gmail.com).» y «Mínimo 8 caracteres» (contraseña). «Continuar» sigue deshabilitado hasta corregir todo. | L19: Pendiente | Q19: src/modules/signup/pages/SignUpPage.tsx; src/shared/utils/email.ts (emailError)
A20: ACC-014 | B20: Acceso y cuenta | C20: Registro del dueño | D20: Campos obligatorios y teléfono con país en «Tu negocio y tu primera cuenta» | E20: Validación | F20: Media | G20: Sin sesión | H20: Paso 3 de 3 del registro, con plan elegido. | I20: 1. Dejar vacíos «Sector» y «Categoría» 2. Escribir un teléfono inválido en «Teléfono (opcional)» con Colombia 3. Corregir el teléfono a un celular válido 4. Completar «Sector» y «Categoría» | J20: Teléfono inválido: 123 456; válido: 300 123 4567 (🇨🇴 +57) | K20: «Crear mi negocio» está deshabilitado mientras falten «Nombre del negocio», «Sector» o «Categoría», o el teléfono sea inválido. El teléfono inválido muestra «Revisa el número: en Colombia, un celular empieza por 3 y tiene 10 dígitos (un fijo, por 60).». El válido se guarda normalizado como +573001234567. | L20: Pendiente | Q20: src/modules/signup/pages/SignUpPage.tsx; src/shared/utils/phone.ts; ADR 0039
A21: ACC-015 | B21: Acceso y cuenta | C21: Registro del dueño | D21: Registrarse con un correo que ya tiene usuario muestra cómo entrar | E21: Negativo | F21: Media | G21: Sin sesión | H21: Ya existe un usuario con laura@negocio.co. | I21: 1. Completar los 3 pasos del registro con ese correo 2. Pulsar «Crear mi negocio» | J21: Correo: laura@negocio.co | K21: No se crea nada y aparece «Ese correo ya tiene usuario en Quanela. Inicia sesión.». El enlace «¿Ya tienes usuario? Inicia sesión» lleva a /login. | L21: Pendiente | Q21: src/modules/signup/pages/SignUpPage.tsx (submit)
A22: ACC-016 | B22: Acceso y cuenta | C22: Registro por teléfono | D22: Registro con teléfono y código SMS, con reenvío y código incorrecto | E22: Funcional | F22: Media | G22: Sin sesión | H22: Método teléfono activo; el número recibe SMS de prueba. | I22: 1. En /registro pulsar «Continuar con teléfono» 2. Elegir 🇨🇴 Colombia, escribir el celular y pulsar «Enviarme el código» 3. Escribir un código equivocado de 6 dígitos y pulsar «Verificar» 4. Esperar a que «Reenviar en N s» cambie a «Reenviar el código» 5. Escribir el código correcto y pulsar «Verificar» | J22: Celular: 300 123 4567; código erróneo: 000000 | K22: «Verificar» se habilita con 6 dígitos (solo números). El código erróneo muestra «El código no es correcto o ya venció. Pide uno nuevo.». El reenvío se habilita a los 60 s. Con el código correcto el registro sigue al paso del plan o del negocio, con «Entraste como +573001234567». | L22: Pendiente | Q22: src/modules/signup/components/OwnerMethods.tsx; src/modules/signup/ownerAuth.ts; ADR 0025
A23: ACC-017 | B23: Acceso y cuenta | C23: Registro del dueño | D23: Un dueño que ya tiene negocio no puede crear un segundo | E23: Negativo | F23: Alta | G23: SUPER_ADMIN (dueño) | H23: Laura ya creó «Hamburguesas La Esquina» y tiene la sesión abierta. | I23: 1. Abrir quanela.com/registro con la sesión abierta | J23: Correo: laura@negocio.co | K23: Se redirige a /app (su cuenta). No aparece el formulario y no se crea otra organización: una persona es dueña de una sola (si se repite la creación, se devuelve la misma cuenta). | L23: Pendiente | Q23: src/modules/signup/pages/SignUpPage.tsx (D4); supabase/tests/signup.sql ('Quien ya es dueño no crea una segunda organización')
A24: ACC-018 | B24: Acceso y cuenta | C24: Registro del dueño | D24: Registrarse con el correo de una invitación pendiente se bloquea | E24: Negativo | F24: Media | G24: Sin sesión | H24: Un ADMIN creó a «Mario Ruiz» (mario@negocio.co) y su usuario sigue «Pendiente». | I24: 1. En /registro, registrarse con mario@negocio.co 2. Confirmar el correo y volver a la app | J24: Correo: mario@negocio.co | K24: No se crea el negocio ni un segundo perfil. Aparece «No pudimos terminar» con el mensaje de invitación pendiente («tienes una invitación pendiente; actívala con el enlace que te enviaron»). Revisar que no se vea el prefijo técnico «PENDING_INVITATION:». | L24: Pendiente | Q24: supabase/tests/owner_signup.sql ('Invitations'); supabase/migrations/20261005100000_dk_owner_signup_methods.sql; src/modules/signup/pages/SignUpConfirmedPage.tsx
A25: ACC-019 | B25: Acceso y cuenta | C25: Enlace para crear contraseña | D25: Crear la contraseña desde un enlace de /set-password | E25: Validación | F25: Media | G25: Sin sesión | H25: Enlace de contraseña generado desde el portal (vigente 1 hora, un solo uso). | I25: 1. Abrir el enlace 2. Escribir contraseñas distintas en «Nueva contraseña» y «Repítela» y pulsar «Guardar contraseña» 3. Escribir la misma contraseña anterior en los dos campos 4. Escribir una contraseña nueva válida en los dos 5. Volver a abrir el mismo enlace | K25: Distintas: «Las contraseñas no coinciden.». Igual a la anterior: «Usa una contraseña distinta a la anterior.». Válida: «Contraseña guardada» con «Entrar a Quanela». Reabrir el enlace: «El enlace ya se usó o venció» con «Los enlaces para crear contraseña son de un solo uso y vencen en poco tiempo...». | L25: Pendiente | Q25: src/modules/auth/pages/SetPasswordPage.tsx; supabase/tests/password_link.sql
A26: ACC-020 | B26: Acceso y cuenta | C26: Cambiar de rol | D26: Una persona con dos roles cambia de rol desde el indicador y la interfaz se adapta | E26: Funcional | F26: Alta | G26: CAJA + COCINA | H26: Andrés tiene CAJA (predeterminado) y COCINA en la misma cuenta. | I26: 1. Pulsar el indicador «Cuenta · CAJA» arriba 2. En «Trabajar como», elegir COCINA 3. Revisar el menú lateral y la pantalla actual 4. Con el menú de usuario → «Cambiar de rol», volver a CAJA | J26: Usuario: andres@negocio.co | K26: Aparece el aviso «Ahora trabajas como COCINA.». El menú muestra solo Operación y Catálogo. Si la pantalla actual no es del rol nuevo (p. ej. Clientes), lleva a su inicio (Operación → Cocina). Al volver a CAJA reaparecen Inicio, Clientes e Insights. | L26: Pendiente | Q26: src/app/AccountSwitcher.tsx (RoleList); src/app/AppLayout.tsx; content/help/intro/roles.md
A27: ACC-021 | B27: Acceso y cuenta | C27: Menú de usuario | D27: El menú de usuario se usa con el teclado | E27: Accesibilidad | F27: Media | G27: ADMIN | H27: Sesión iniciada en escritorio. | I27: 1. Llevar el foco con Tab al avatar (aria-label «Menú de usuario: {nombre}») y pulsar Enter 2. Recorrer con ↑/↓ 3. En «Apariencia» pulsar → 4. Pulsar ← para cerrar el submenú 5. Pulsar Esc | K27: El menú se abre con Enter, ↑/↓ recorren las opciones, → abre el submenú lateral, ← lo cierra y Esc cierra el menú. El foco vuelve al avatar. | L27: Pendiente | Q27: ADR 0023 (sección 2); src/shared/ui/MenuPanel.tsx; src/app/help/HelpDialogs.tsx (atajos)
A28: ACC-022 | B28: Acceso y cuenta | C28: Mi perfil | D28: Cambiar la contraseña desde «Mi perfil» | E28: Validación | F28: Alta | G28: CAJA | H28: Sesión iniciada con correo y contraseña. | I28: 1. Menú de usuario → «Mi perfil» → tarjeta «Contraseña» 2. Escribir mal la «Contraseña actual», una nueva válida, y pulsar «Cambiar contraseña» 3. Escribir 7 caracteres en «Nueva contraseña» 4. Escribir en «Nueva contraseña» la misma contraseña actual 5. Escribir en «Repite la nueva» un valor distinto 6. Completar todo bien y pulsar «Cambiar contraseña» | K28: Actual incorrecta: aviso «La contraseña actual no es correcta». Se ven «Mínimo 8 caracteres», «Debe ser distinta de la actual» y «No coincide». Con todo correcto: «Contraseña actualizada.» y los campos se vacían. | L28: Pendiente | Q28: src/modules/profile/pages/ProfilePage.tsx; src/modules/profile/api/profile.ts
A29: ACC-023 | B29: Acceso y cuenta | C29: Usuario sin negocio | D29: Un usuario que no pertenece a ningún negocio ve un mensaje con la marca Quanela | E29: UI/UX | F29: Baja | G29: Usuario autenticado sin negocio | H29: Usuario de prueba con sesión válida pero sin perfil en ninguna organización. | I29: 1. Iniciar sesión con ese usuario 2. Leer el mensaje de la pantalla | J29: sinnegocio@prueba.co | K29: El mensaje dice que el usuario aún no pertenece a ningún negocio en Quanela (no «Dark Kitchen») y ofrece cerrar sesión. | L29: Pendiente | Q29: src/modules/auth/pages/NoProfilePage.tsx
A30: ACC-024 | B30: Acceso y cuenta | C30: Regreso tras iniciar sesión | D30: Tras iniciar sesión se vuelve a la página protegida que se había pedido | E30: UI/UX | F30: Media | G30: CAJA | H30: Sin sesión. Usuario CAJA activo. | I30: 1. Abrir directamente la URL de Clientes del negocio 2. Iniciar sesión en el login al que redirige 3. Ver a qué pantalla llega | K30: Después de iniciar sesión se abre Clientes, la página que se pidió (la URL del login lleva ?next=). Hoy se llega a la pantalla de inicio del rol: anotar como defecto si pasa. | L30: Pendiente | Q30: src/modules/auth; src/app/routes.tsx
A31: EQP-001 | B31: Equipo | C31: Crear usuario (invitación) | D31: Un ADMIN crea un usuario y obtiene el enlace de activación | E31: Funcional | F31: Alta | G31: ADMIN | H31: ADMIN en una cuenta con plan disponible para más usuarios. | I31: 1. Abrir «Usuarios» y pulsar «Crear usuario» 2. Escribir «Nombre» y «Correo» 3. En «Roles en esta cuenta» marcar COCINA 4. Pulsar «Crear usuario» 5. En «Usuario creado», pulsar «Copiar» 6. Cerrar y buscar a la persona en la lista | J31: Sofía Martínez; sofia.cocina@negocio.co; rol COCINA | K31: Aparece «Usuario creado» con el enlace y el texto «Envíale este enlace a Sofía Martínez (sofia.cocina@negocio.co) por WhatsApp o correo... Vence en 7 días.» y «Por seguridad no se vuelve a mostrar...». «Copiar» muestra «Enlace copiado.». En la lista, Sofía aparece con estado «Pendiente». | L31: Pendiente | Q31: content/help/getting-started/invite-team.md; src/modules/organization/components/UserDrawer.tsx; src/modules/organization/components/ActivationLinkModal.tsx; supabase/tests/org_users.sql
A32: EQP-002 | B32: Equipo | C32: Crear usuario (invitación) | D32: Validaciones del formulario «Crear usuario» | E32: Validación | F32: Alta | G32: ADMIN | H32: Panel «Crear usuario» abierto en un negocio con 2 cuentas. | I32: 1. Escribir «S» en «Nombre» 2. Escribir «sofia@negocio» en «Correo» 3. Desmarcar todas las cuentas 4. Marcar una cuenta y quitarle todos los roles | J32: Nombre: S; correo: sofia@negocio | K32: Se ven «Mínimo 2 caracteres», «Falta el dominio del correo (por ejemplo, @gmail.com).», «Asígnale al menos una cuenta.» y «Elige al menos un rol.». El botón «Crear usuario» queda deshabilitado mientras haya errores. | L32: Pendiente | Q32: src/modules/organization/components/UserDrawer.tsx
A33: EQP-003 | B33: Equipo | C33: Activación de usuario | D33: La persona invitada activa su usuario con el enlace y entra a su cuenta | E33: Funcional | F33: Alta | G33: Sin sesión (invitado) | H33: Existe el enlace vigente de Sofía (COCINA). Sofía no tiene usuario en Quanela. | I33: 1. Abrir el enlace /activar/{token} 2. Verificar el encabezado 3. Escribir una contraseña de 7 caracteres en «Crea tu contraseña» 4. Completarla a 8 o más caracteres 5. Pulsar «Activar mi usuario» | J33: Contraseña de prueba de 8+ caracteres | K33: Se ve «Activa tu usuario», el nombre del negocio y «Hola, Sofía Martínez · sofia.cocina@negocio.co». El «Correo» es de solo lectura. «Activar mi usuario» se habilita con 8 caracteres o más. Al activar entra a su cuenta como COCINA (Operación → Cocina) y en Usuarios su estado pasa a «Activo». | L33: Pendiente | Q33: src/modules/invitations/pages/ActivationPage.tsx; supabase/tests/org_users.sql ('Activación')
A34: EQP-004 | B34: Equipo | C34: Activación de usuario | D34: Enlaces de activación usados, vencidos, reemplazados o incompletos | E34: Negativo | F34: Alta | G34: Sin sesión | H34: Tener 4 enlaces de prueba: uno ya usado, uno vencido (más de 7 días), uno reemplazado por «Generar enlace nuevo» y uno con el token cortado. | I34: 1. Abrir cada enlace en una ventana privada | K34: Usado: «Este enlace ya se usó. Si es tuyo, solo inicia sesión.». Vencido: «Este enlace venció. Pide a tu administrador uno nuevo.». Reemplazado: «Este enlace fue reemplazado por uno más nuevo. Usa el último que te enviaron.». Cortado: «Enlace no válido» y «Revisa que el enlace esté completo o pide uno nuevo a tu administrador.». Todos ofrecen «Ir a iniciar sesión» y ninguno activa al usuario. | L34: Pendiente | Q34: src/modules/invitations/pages/ActivationPage.tsx (STATUS_MESSAGE); supabase/tests/org_users.sql ('Reusar el enlace')
A35: EQP-005 | B35: Equipo | C35: Activación de usuario | D35: «Generar enlace nuevo» invalida el enlace anterior | E35: Seguridad | F35: Alta | G35: ADMIN | H35: Sofía está «Pendiente» y tiene un enlace vigente (enlace 1). | I35: 1. Abrir la ficha de Sofía en Usuarios 2. Verificar el texto «Pendiente de activación · el enlace vence el {fecha}» 3. Pulsar «Generar enlace nuevo» y copiar el enlace 2 4. Abrir el enlace 1 en una ventana privada 5. Abrir el enlace 2 | K35: El enlace 1 muestra «Este enlace fue reemplazado por uno más nuevo. Usa el último que te enviaron.». El enlace 2 permite activar. | L35: Pendiente | Q35: content/help/getting-started/invite-team.md; src/modules/organization/components/UserDrawer.tsx; supabase/tests/password_link.sql ('Old activation link revoked')
A36: EQP-006 | B36: Equipo | C36: Activación de usuario | D36: Abrir un enlace de activación con la sesión de otro correo no lo activa | E36: Seguridad | F36: Alta | G36: CAJA (otra persona) | H36: Sesión abierta como camila.caja@negocio.co. Enlace vigente de Sofía. | I36: 1. Con esa sesión, abrir el enlace de Sofía | K36: Aparece «Entraste como camila.caja@negocio.co, pero este enlace es para sofia.cocina@negocio.co. Cierra sesión y entra con ese correo.» con el botón «Cerrar sesión». La invitación no se activa. | L36: Pendiente | Q36: src/modules/invitations/pages/ActivationPage.tsx; supabase/tests/org_users.sql ('Activar con otro correo')
A37: EQP-007 | B37: Equipo | C37: Activación de usuario | D37: Una persona que ya tiene usuario en otro negocio se une con su mismo perfil | E37: Integración | F37: Media | G37: CAJA (en otro negocio) | H37: Andrés es CAJA en el negocio A. El ADMIN del negocio B lo invita como COCINA. | I37: 1. Abrir el enlace de B sin sesión 2. Pulsar «Iniciar sesión» 3. Iniciar sesión con su correo y contraseña 4. Pulsar «Activar y entrar a {Negocio B}» 5. Abrir «Tus cuentas» | J37: Correo: andres@negocio.co | K37: Sin sesión se ve «Ya tienes usuario en Quanela. Inicia sesión con tu correo para unirte a {Negocio B}.» y la opción «Aún no tengo contraseña: envíame un enlace». Tras iniciar sesión vuelve al enlace (login?next=/activar/...). Al activar entra a la cuenta de B como COCINA. En «Tus cuentas» ve las dos cuentas con un solo usuario y perfil. | L37: Pendiente | Q37: src/modules/invitations/pages/ActivationPage.tsx; supabase/tests/org_users.sql ('Identidad')
A38: EQP-008 | B38: Equipo | C38: Usuarios | D38: Cambiar los roles de una persona y con cuál «Entra como» | E38: Funcional | F38: Alta | G38: ADMIN | H38: Negocio con 2 cuentas. Camila tiene CAJA en «Brasa Centro». | I38: 1. Abrir «Usuarios» y pulsar sobre Camila 2. Agregarle COCINA en «Brasa Centro» 3. En «Entra como», elegir CAJA 4. Pulsar «Aplicar a todas las cuentas» 5. Pulsar «Guardar cambios» | J38: Usuario: camila.caja@negocio.co | K38: Aparece «Cambios guardados.». Camila tiene CAJA y COCINA en las dos cuentas y entra como CAJA. En su próxima sesión, el indicador permite cambiar entre los dos roles. | L38: Pendiente | Q38: content/help/team/users-and-roles.md; src/modules/organization/components/UserDrawer.tsx
A39: EQP-009 | B39: Equipo | C39: Usuarios | D39: Desactivar y volver a activar a una persona | E39: Funcional | F39: Alta | G39: SUPER_ADMIN (dueño) | H39: Camila está activa en 2 cuentas. | I39: 1. Abrir la ficha de Camila y pulsar «Desactivar» 2. Leer el diálogo «Desactivar usuario» y pulsar «Sí, desactivar» 3. En otra ventana, intentar entrar como Camila 4. Volver a la ficha y pulsar «Activar» → «Sí, activar» | K39: El diálogo dice «Camila ... pierde el acceso de inmediato. Aplica a todas tus cuentas.». Aparece «{nombre} ya no tiene acceso.» y su estado pasa a «Desactivado». Camila no puede operar en ninguna cuenta. Al activarla: «{nombre} vuelve a tener acceso.» con los mismos roles. | L39: Pendiente | Q39: src/modules/organization/components/UserDrawer.tsx; supabase/tests/org_users.sql ('Desactivar')
A40: EQP-010 | B40: Equipo | C40: Usuarios | D40: Nadie cambia sus propios roles ni su estado, y el SUPER_ADMIN no se puede desactivar | E40: Permisos | F40: Alta | G40: ADMIN / SUPER_ADMIN | H40: Laura es SUPER_ADMIN (creó el negocio). Pablo es ADMIN invitado. | I40: 1. Como Pablo, abrir su propia ficha en «Usuarios» 2. Como Pablo, abrir la ficha de Laura 3. Por API, como Pablo, llamar a la función para desactivar a Laura | K40: En su propia ficha, Pablo ve la insignia «Tú», con los roles deshabilitados y sin «Desactivar» ni «Quitar de esta cuenta». En la ficha de Laura se ve la insignia «SUPER_ADMIN», la nota de que es intransferible, y no aparecen «Desactivar» ni «Quitar». La API rechaza el cambio. | L40: Pendiente | Q40: src/modules/organization/components/UserDrawer.tsx (lockedStatus/lockedRoles); supabase/tests/org_users.sql ('SUPER_ADMIN'); supabase/tests/account_scope.sql ('Cannot remove yourself')
A41: EQP-011 | B41: Equipo | C41: Usuarios | D41: No se puede asignar un rol con permisos que uno no tiene | E41: Permisos | F41: Alta | G41: Rol propio con team.manage (sin todos los permisos) | H41: Existe un rol propio «ENCARGADO» con team.manage pero sin permisos de configuración. El ADMIN tiene todos. | I41: 1. Entrar como el usuario con rol ENCARGADO 2. Abrir «Crear usuario» 3. Pasar el cursor sobre el rol ADMIN en la lista de roles | K41: ADMIN aparece deshabilitado con el tooltip «Tiene permisos que tú no tienes». Si se fuerza por API, la base responde «No puedes asignar un rol con permisos que tú no tienes (...)». | L41: Pendiente | Q41: src/modules/organization/components/UserDrawer.tsx; content/help/team/users-and-roles.md; supabase/migrations (dk_set_member_roles)
A42: EQP-012 | B42: Equipo | C42: Usuarios | D42: «Quitar de esta cuenta» y «Cancelar la invitación a esta cuenta» solo afectan a la cuenta actual | E42: Funcional | F42: Media | G42: ADMIN | H42: Camila (activa) está en «Brasa Centro» y «Brasa Norte». Mario (pendiente) está invitado a «Brasa Centro». | I42: 1. En «Brasa Centro», abrir a Camila → «Quitar de esta cuenta» → «Sí, quitar» 2. Abrir a Mario y revisar el texto del botón 3. Cambiar a «Brasa Norte» y abrir «Usuarios» | K42: Aparece «Camila ... salió de esta cuenta.» y el diálogo indica que su historial se conserva. Para Mario el botón dice «Cancelar la invitación a esta cuenta». En «Brasa Norte», Camila sigue activa con su rol. | L42: Pendiente | Q42: src/modules/organization/components/UserDrawer.tsx; supabase/tests/account_scope.sql ('Working in A never removes someone from B')
A43: EQP-013 | B43: Equipo | C43: Diálogos (accesibilidad) | D43: En el panel «Crear usuario» el foco no salta mientras se escribe, y Esc cierra | E43: Regresión | F43: Media | G43: ADMIN | H43: Fallo conocido: el foco saltaba a la ✕ en cada tecla. | I43: 1. Abrir «Crear usuario» 2. Escribir un nombre largo letra por letra en «Nombre» 3. Pulsar Tab muchas veces 4. Pulsar Esc | J43: Nombre: María Fernanda Castaño | K43: El foco se queda en «Nombre» mientras se escribe. Tab recorre solo los elementos del panel (el foco queda atrapado). Esc cierra el panel y el foco vuelve al botón «Crear usuario». | L43: Pendiente | Q43: src/shared/hooks/useDialogA11y.ts (comentario del fallo corregido); src/shared/ui/Drawer.tsx
A44: EQP-014 | B44: Equipo | C44: Roles propios | D44: Crear un rol propio copiando permisos de una plantilla | E44: Funcional | F44: Alta | G44: SUPER_ADMIN (dueño) | H44: Pestaña «Roles y permisos» de «Usuarios». | I44: 1. Pulsar «Nuevo rol» 2. Escribir «Mesero de turno» en «Nombre» 3. En «Copiar permisos de», elegir CAJA 4. Quitar un permiso y agregar otro 5. Pulsar «Crear rol» 6. Abrir «Crear usuario» y revisar los roles disponibles | J44: Nombre: Mesero de turno | K44: El nombre se guarda en mayúsculas con guiones bajos (MESERO_DE_TURNO). Aparece «Rol creado.» y la tarjeta en «Roles propios» con su número de permisos. El rol se puede asignar en «Crear usuario». | L44: Pendiente | Q44: content/help/team/users-and-roles.md; src/modules/organization/components/RoleEditorDrawer.tsx; src/shared/rbac/roles.ts (normalizeRoleName)
A45: EQP-015 | B45: Equipo | C45: Roles propios | D45: Nombre de rol reservado, repetido o vacío | E45: Validación | F45: Media | G45: SUPER_ADMIN (dueño) | H45: Existe el rol propio MESERO_DE_TURNO. | I45: 1. «Nuevo rol» con nombre «admin» → «Crear rol» 2. «Nuevo rol» con nombre «Mesero de turno» → «Crear rol» 3. «Nuevo rol» con nombre «M» | K45: «admin» se rechaza con «Ese nombre está reservado» y el nombre repetido con «Ya existe un rol con ese nombre en la organización» (aviso de error «No se pudo guardar el rol» si no llega el mensaje). Con 1 carácter, «Crear rol» queda deshabilitado. No se crea ningún rol. | L45: Pendiente | Q45: supabase/migrations (dk_save_role: errores); src/modules/organization/components/RoleEditorDrawer.tsx
A46: EQP-016 | B46: Equipo | C46: Roles propios | D46: No se puede eliminar un rol que alguien tiene asignado | E46: Negativo | F46: Media | G46: SUPER_ADMIN (dueño) | H46: El rol MESERO_DE_TURNO está asignado a una persona. | I46: 1. En la tarjeta del rol pulsar «Eliminar» 2. Leer el diálogo «Eliminar rol» y pulsar «Sí, eliminar» 3. Cambiarle el rol a esa persona y repetir | K46: La primera vez falla con «El rol está asignado a personas; cámbialas antes de eliminarlo». Cuando nadie lo tiene, se elimina con el aviso «Rol MESERO_DE_TURNO eliminado.». | L46: Pendiente | Q46: src/modules/organization/components/RolesPanel.tsx; content/help/team/users-and-roles.md
A47: EQP-017 | B47: Equipo | C47: Turnos | D47: Programar un turno nocturno con descanso | E47: Funcional | F47: Alta | G47: GERENTE | H47: La cuenta tiene al menos un miembro con rol COCINA. | I47: 1. Abrir «Personal» y pulsar «Nuevo turno» 2. Elegir la persona, «Rol en este turno» COCINA y el «Día» 3. «Entra» 18:00 y «Sale» 02:00 4. «Descanso» 30 y una «Nota» 5. Pulsar «Crear turno» | J47: Persona: Sofía Martínez; nota: «Ej. cubre a Laura, abre la cocina» | K47: Bajo «Sale» aparece «Termina al día siguiente.». Al crear: «Turno creado.». El turno se ve en la pestaña «Semana» y sus horas planificadas descuentan el descanso en «Horas». | L47: Pendiente | Q47: content/help/team/shifts.md; src/modules/staff/components/ShiftDrawer.tsx; supabase/tests/staff_shifts.sql ('Overnight shift')
A48: EQP-018 | B48: Equipo | C48: Turnos | D48: Reglas del turno: cruce de horario, duración y descanso | E48: Validación | F48: Alta | G48: GERENTE | H48: Sofía ya tiene un turno de 08:00 a 14:00 hoy (en esta u otra cuenta del negocio). | I48: 1. Crear para Sofía un turno de 12:00 a 18:00 el mismo día 2. Crear un turno de 06:00 a 23:00 (17 h) 3. Crear un turno de 2 h con «Descanso» de 180 minutos | K48: Mensajes: «Esa persona ya tiene un turno que se cruza con ese horario (en esta u otra cuenta).», «Un turno dura entre 15 minutos y 16 horas, y termina después de empezar.» y «El descanso debe ser menor que el turno (máximo 4 horas).». No se guarda ninguno. | L48: Pendiente | Q48: src/modules/staff/api/staff.ts (shiftErrorMessage); supabase/tests/staff_shifts.sql ('Rules')
A49: EQP-019 | B49: Equipo | C49: Turnos | D49: Marcar entrada y salida en «Mis turnos», también sin turno programado | E49: Funcional | F49: Alta | G49: COCINA | H49: Sofía no tiene turno programado ahora. | I49: 1. Menú de usuario → «Mis turnos» 2. Pulsar «Marcar entrada» 3. Intentar marcar entrada otra vez por API 4. Pulsar «Marcar salida» | K49: Antes de marcar: «No tienes turno programado ahora.». Al marcar: «Entrada marcada.» y la tarjeta muestra «Turno sin programar · {horas}». La segunda entrada se rechaza con «Ya marcaste entrada: marca la salida de tu turno abierto». «Marcar salida» muestra «Salida marcada.». | L49: Pendiente | Q49: src/modules/staff/components/ClockCard.tsx; content/help/team/shifts.md; supabase/tests/staff_shifts.sql ('Clock')
A50: EQP-020 | B50: Equipo | C50: Turnos | D50: COCINA no ve «Personal» y solo ve sus propios turnos | E50: Permisos | F50: Alta | G50: COCINA | H50: Sofía (COCINA) tiene turnos. Otros compañeros también. | I50: 1. Revisar el menú lateral 2. Abrir directo /k/{cuenta}/staff 3. Abrir «Mis turnos» | K50: «Personal» no aparece en el menú. La URL directa lleva a su inicio (Operación → Cocina). En «Mis turnos» solo ve sus turnos; no puede crear, editar ni copiar turnos (la base lo rechaza). | L50: Pendiente | Q50: src/app/navigation.ts (isSectionAllowed); supabase/tests/staff_shifts.sql ('Access')
A51: CFG-001 | B51: Configuración | C51: Configuración → General | D51: Cambiar el nombre y la zona horaria de la cuenta con la barra de guardado | E51: UI/UX | F51: Alta | G51: ADMIN | H51: Cuenta «Brasa Centro» en zona Colombia (Bogotá). | I51: 1. Abrir «Configuración» → «General» 2. En «Esta cuenta», cambiar «Nombre» a «Brasa Centro Calle 72» 3. Cambiar «Zona horaria» a «México (Ciudad de México)» 4. Pulsar «Descartar» 5. Repetir los cambios y pulsar «Guardar cambios» | K51: «Descartar» y «Guardar cambios» aparecen solo cuando hay cambios. «Descartar» vuelve a los valores guardados. Al guardar se ve «Guardando…», luego «Guardado» y el aviso «Datos de la cuenta guardados.». El nombre nuevo aparece en el indicador de arriba. | L51: Pendiente | Q51: content/help/settings/settings.md; src/modules/settings/pages/KitchenGeneralPage.tsx; src/shared/ui/SaveBar.tsx; ADR 0026
A52: CFG-002 | B52: Configuración | C52: Configuración → General | D52: Validación del «Identificador (URL)» de la cuenta | E52: Validación | F52: Media | G52: ADMIN | H52: Existe otra cuenta con identificador brasa-norte. | I52: 1. En «Identificador (URL)» escribir «br» 2. Escribir «Brasa Centro» (con espacio) 3. Escribir «brasa-norte» y guardar 4. Escribir «brasa-centro-72» y guardar | K52: Mensajes: «Mínimo 3 caracteres» y «Solo minúsculas, números y guiones (sin espacios ni tildes)» (las mayúsculas se convierten solas a minúsculas). Duplicado: «Ese identificador ya lo usa otra cuenta.». Válido: guarda y la dirección pasa a /k/brasa-centro-72/settings/general. | L52: Pendiente | Q52: src/modules/settings/pages/KitchenGeneralPage.tsx; src/shared/kitchen/slug.ts
A53: CFG-003 | B53: Configuración | C53: Secciones de Configuración | D53: Cada rol ve solo sus secciones de Configuración | E53: Permisos | F53: Alta | G53: SUPER_ADMIN, ADMIN, GERENTE, CAJA | H53: Un mismo negocio con usuarios de cada rol. | I53: 1. Entrar con cada rol y abrir «Configuración» 2. Como GERENTE, abrir directo /k/{cuenta}/settings/activity 3. Como CAJA, abrir directo /k/{cuenta}/settings/general | K53: SUPER_ADMIN: General (con «Tu negocio» y «Zona de peligro»), Facturación, IA y voz, Integraciones y Actividad. ADMIN invitado: General, IA y voz, Integraciones y Actividad, sin Facturación ni «Zona de peligro». GERENTE: General, IA y voz e Integraciones (sin Actividad); la URL de Actividad lleva a la primera sección permitida. CAJA no ve «Configuración» y la URL lleva a su inicio. | L53: Pendiente | Q53: src/modules/settings/sections.ts; src/modules/settings/pages/SettingsLayout.tsx; supabase/tests/permission_catalog.sql ('Gerente: configuración · sin auditoría · sin equipo')
A54: CFG-004 | B54: Configuración | C54: Multi-cocina | D54: Desactivar una cuenta desde «Zona de peligro» y reactivarla desde «Tus cuentas» | E54: Funcional | F54: Alta | G54: SUPER_ADMIN (dueño) | H54: Negocio con 2 cuentas; Camila (CAJA) trabaja en «Brasa Norte». | I54: 1. En «Brasa Norte» → «Configuración» → «General» → «Zona de peligro», pulsar «Desactivar cuenta» 2. Pulsar «Sí, desactivar» 3. Entrar como Camila a /k/brasa-norte 4. Como dueño, abrir «Tus cuentas» y pulsar «Activar» en «Brasa Norte» | K54: Aparece «Cuenta desactivada.». Camila ve «Cuenta desactivada» («Brasa Norte está desactivada...») con «Ver mis cuentas». En «Tus cuentas» la tarjeta tiene la insignia «Desactivada». Al activar: «Brasa Norte está activa de nuevo.» y los datos siguen intactos. | L54: Pendiente | Q54: src/modules/settings/components/AccountStatusCard.tsx; src/app/KitchenInactivePage.tsx; src/modules/kitchens/pages/KitchenSelectorPage.tsx
A55: CFG-005 | B55: Configuración | C55: Multi-cocina | D55: Crear una cuenta nueva y respetar el tope del plan | E55: Funcional | F55: Alta | G55: SUPER_ADMIN (dueño) | H55: Plan con espacio para una cuenta más. | I55: 1. Abrir «Tus cuentas» y pulsar «Nueva cuenta» 2. Escribir «B» en «Nombre» y luego «Brasa Sur» 3. Revisar el «Identificador (URL)» propuesto y pulsar crear 4. Llenar el tope del plan e intentar crear otra cuenta | J55: Nombre: Brasa Sur | K55: Con 1 carácter: «Mínimo 2 caracteres». El hint muestra «La cuenta quedará en /k/brasa-sur». Al crear: «Cuenta "Brasa Sur" creada.» y se abre la cuenta nueva. Por encima del tope: «Tu plan permite hasta N cuentas. Para agregar más, cambia de plan.». Un identificador repetido muestra «Ya existe una cuenta con ese identificador.». | L55: Pendiente | Q55: src/modules/kitchens/components/CreateKitchenDialog.tsx; ADR 0007; ADR 0010
A56: SEG-001 | B56: Roles y seguridad | C56: Inicio y menú por rol | D56: Cada plantilla de rol empieza en su pantalla y ve solo sus módulos | E56: Permisos | F56: Alta | G56: ADMIN, GERENTE, CAJA, COCINA, INVENTARIO, DOMICILIARIO | H56: Un usuario de prueba por cada rol en la misma cuenta. | I56: 1. Iniciar sesión con cada rol 2. Anotar la pantalla de inicio 3. Anotar los ítems del menú lateral | K56: ADMIN: Inicio, todo el menú. GERENTE: Inicio, todo menos «Usuarios». CAJA: Operación → Tablero; Inicio, Operación, Catálogo, Clientes, Insights. COCINA: Operación → Cocina; Operación, Catálogo. INVENTARIO: Inicio; Inicio, Catálogo, Abastecimiento, Insights. DOMICILIARIO: Operación → Despacho; solo Operación (Despacho). | L56: Pendiente | Q56: content/help/intro/roles.md; src/app/navigation.ts (homeSection, NAV_ITEMS); src/shared/rbac/roles.ts
A57: SEG-002 | B57: Roles y seguridad | C57: Rutas por rol | D57: Abrir una sección no permitida por URL lleva al inicio del rol | E57: Permisos | F57: Alta | G57: CAJA, INVENTARIO | H57: Sesión como CAJA y luego como INVENTARIO. | I57: 1. Como CAJA, abrir /k/{cuenta}/users 2. Como CAJA, abrir /k/{cuenta}/supply/stock 3. Como INVENTARIO, abrir /k/{cuenta}/customers | K57: No se muestra ninguna pantalla de «No autorizado» ni datos: CAJA vuelve a Operación (Tablero) e INVENTARIO a Inicio. La base rechaza igual las lecturas por API. | L57: Pendiente | Q57: src/app/AppLayout.tsx (isSectionAllowed); src/app/navigation.ts
A58: SEG-003 | B58: Roles y seguridad | C58: Botones deshabilitados | D58: Un botón que el rol no puede usar aparece gris y explica por qué | E58: Permisos | F58: Media | G58: COCINA | H58: Hay un pedido pendiente de confirmar visible en Operación. | I58: 1. Como COCINA, abrir Operación 2. Pasar el cursor sobre la acción de confirmar o crear pedido | K58: El botón está gris y el tooltip dice «Solo caja o administración confirma pedidos» (o «Solo caja o administración crea pedidos»). No se ejecuta ninguna acción. | L58: Pendiente | Q58: content/help/intro/roles.md; src/modules/orders/lib/permissions.ts (ACTION_DENIED_REASON)
A59: SEG-004 | B59: Roles y seguridad | C59: Aislamiento entre cuentas | D59: Los datos de una cuenta no se ven desde otra cuenta del mismo negocio | E59: Seguridad | F59: Alta | G59: CAJA en A / CAJA en B | H59: Negocio con cuentas A y B. Camila es CAJA solo en A y Julián es CAJA solo en B. | I59: 1. Como Camila, crear en A el cliente «Cliente Solo De A» con teléfono +57 300 123 4567 2. Como Julián, buscar ese cliente en Clientes de B 3. Como Julián, crear un cliente con el mismo teléfono en B | J59: Teléfono: +57 300 123 4567 | K59: Julián no ve el cliente de A. Al usar el mismo teléfono en B se crea otro cliente distinto (no se reutiliza el de A). Lo mismo pasa con pedidos, inventario, catálogo y turnos. | L59: Pendiente | Q59: supabase/tests/multikitchen_isolation.sql; ADR 0007
A60: SEG-005 | B60: Roles y seguridad | C60: Aislamiento entre cuentas | D60: Usuarios y Actividad muestran solo la cuenta actual, aunque el ADMIN esté en varias | E60: Seguridad | F60: Alta | G60: ADMIN (en A y B) | H60: Pablo es ADMIN en A y B. «Solo En B» es miembro solo de B. Hay eventos de bitácora en las dos cuentas. | I60: 1. Como Pablo, trabajando en A, abrir «Usuarios» 2. Abrir «Configuración» → «Actividad» → «Bitácora» 3. Cambiar a la cuenta B y repetir | K60: En A no aparece el miembro que solo está en B, y la bitácora no muestra eventos de B ni ofrece un filtro para elegir otra cuenta. En B pasa lo contrario. | L60: Pendiente | Q60: supabase/tests/account_scope.sql; ADR 0024 (1.3)
A61: SEG-006 | B61: Roles y seguridad | C61: Aislamiento entre negocios (API) | D61: Cambiar el encabezado de cuenta por API no da acceso a otro negocio | E61: Seguridad | F61: Alta | G61: ADMIN (negocio A) | H61: Laura es ADMIN solo en el negocio A. Se conoce el ID de una cuenta y el código del negocio B. Herramientas de desarrollador del navegador. | I61: 1. Con la sesión de Laura, repetir una consulta REST de clientes cambiando el encabezado de cuenta al ID de la cuenta de B 2. Intentar insertar un cliente en la cuenta de B por la API 3. Intentar renombrar el negocio B por la API | J61: Cliente: «Intruso» | K61: La consulta devuelve 0 filas de B, la inserción se rechaza por RLS y el nombre de B no cambia. Conocer el código o el ID de B no da acceso. | L61: Pendiente | Q61: supabase/tests/tenants.sql ('Isolation'); ADR 0005; ADR 0021 (1.1)
A62: SEG-007 | B62: Roles y seguridad | C62: Acceso anónimo a la API | D62: Sin sesión, las funciones de la cuenta no devuelven datos | E62: Seguridad | F62: Alta | G62: Sin sesión | H62: Clave pública (anon) del proyecto, sin token de usuario. | I62: 1. Llamar por REST a dk_account_users 2. Llamar a dk_account_alerts 3. Intentar marcar entrada (clock in) de turno | K62: Todas las llamadas se rechazan (sin datos ni cambios). | L62: Pendiente | Q62: supabase/tests/account_scope.sql ('Anonymous'); supabase/tests/staff_shifts.sql ('Anonymous clock in'); supabase/tests/signup.sql ('Sin sesión')
A63: ADM-001 | B63: Portal de administración | C63: Login del portal | D63: El portal admin rechaza credenciales erróneas y a usuarios que no son Global Admin | E63: Seguridad | F63: Alta | G63: Sin sesión / CAJA | H63: Portal en admin.quanela.com. Camila es un usuario normal de Quanela. | I63: 1. Abrir admin.quanela.com 2. Entrar con una contraseña equivocada y pulsar «Continuar» 3. Entrar con el correo y la contraseña correctos de Camila 4. Pulsar «Volver» | J63: Correo: camila.caja@negocio.co | K63: Con contraseña equivocada: «Correo o contraseña incorrectos.». Con Camila: «Acceso restringido» y «camila.caja@negocio.co no tiene acceso a Quanela Global Admin. Tu sesión en Quanela no cambia.». No se ve ningún dato de la plataforma. | L63: Pendiente | Q63: admin/src/auth/LoginPage.tsx; admin/src/auth/session.tsx; supabase/tests/global_admin.sql
A64: ADM-002 | B64: Portal de administración | C64: Segundo factor (TOTP) | D64: El Global Admin necesita el código TOTP de 6 dígitos para entrar | E64: Seguridad | F64: Alta | G64: Global Admin | H64: Usuario con rol de plataforma SUPERADMIN, sin autenticador registrado. | I64: 1. Iniciar sesión con correo y contraseña 2. Escanear el QR o copiar la clave en una app autenticadora 3. Escribir un código equivocado y pulsar «Activar y entrar» 4. Escribir el código correcto | K64: Sin MFA no se ve ningún dato del portal. «Activar y entrar» solo se habilita con 6 dígitos. Un código equivocado muestra «Código incorrecto. Revisa la hora del teléfono e inténtalo de nuevo.». Con el correcto se entra al Dashboard. En las siguientes entradas solo se pide el código. | L64: Pendiente | Q64: admin/src/auth/LoginPage.tsx; ADR 0019 (D4); supabase/tests/global_admin.sql ('Global Admin without MFA')
A65: ADM-003 | B65: Portal de administración | C65: Crear organización | D65: Crear una organización desde el portal y ver su código y subdominio | E65: Funcional | F65: Alta | G65: Global Admin | H65: Global Admin con MFA. El correo del administrador no tiene organización. | I65: 1. Organizations → «Crear organización» 2. Paso «Organización»: dejar el nombre vacío y elegir nada 3. Completar nombre, «Sector», «Categoría», «Plan», «País» y «Teléfono» 4. Paso «Administrador»: «Nombre completo» y «Correo» 5. Paso «Revisión»: pulsar «Crear organización» | J65: Pizzería Don Tito; Bogotá; 300 123 4567; administrador: Tito Ramírez, tito@donpizza.co | K65: Validaciones: «Entre 2 y 80 caracteres», «Elige el sector», «Elige la categoría», «Elige el plan». El resultado muestra «Código» (6 caracteres), «Subdominio» ({código}.quanela.com), «Plan», «Administrador» con «Pendiente de activación» y el estado de la invitación («Enviada» o «No enviada» con «Copiar enlace»). | L65: Pendiente | Q65: admin/src/pages/CreateOrganizationPage.tsx; admin/src/lib/createOrganization.ts; ADR 0022 (3.3)
A66: ADM-004 | B66: Portal de administración | C66: Detalle de organización | D66: Desactivar una organización exige escribir su nombre exacto | E66: Funcional | F66: Alta | G66: Global Admin | H66: Organización activa «Pizzería Don Tito». | I66: 1. Abrir su detalle y pulsar «Desactivar» 2. Escribir «Pizzeria Don Tito» (sin tilde) en el campo 3. Escribir el nombre exacto y pulsar «Desactivar organización» 4. Abrir {código}.quanela.com 5. Volver al portal y pulsar «Reactivar» | K66: El diálogo «Desactivar Pizzería Don Tito» pide «Escribe Pizzería Don Tito para confirmar». El botón está deshabilitado hasta que el texto coincide exactamente. Tras desactivar, el subdominio muestra «Pizzería Don Tito está desactivado». «Reactivar» devuelve el acceso. | L66: Pendiente | Q66: admin/src/pages/OrganizationDetailPage.tsx; admin/src/components/ui.tsx (ConfirmByName)
A67: ADM-005 | B67: Portal de administración | C67: Enlace para crear contraseña | D67: El Global Admin genera un enlace de contraseña de un solo uso | E67: Seguridad | F67: Media | G67: Global Admin | H67: Usuario activo con inicio de sesión. Otro usuario desactivado. | I67: 1. En el detalle de la organización → pestaña de usuarios, pulsar «Enlace para crear contraseña» del usuario activo 2. Pulsar «Copiar» 3. Generar otro enlace y abrir el primero 4. Intentar generarlo para el usuario desactivado | K67: El modal «Enlace para crear contraseña» dice «Al abrirlo crea una contraseña nueva.» y avisa que es de un solo uso y vence en 1 hora. «Copiar» muestra «Enlace copiado.». El primer enlace deja de servir. Para el usuario desactivado se rechaza («No se pudo generar el enlace» / mensaje de la base). | L67: Pendiente | Q67: admin/src/components/PasswordLinkButton.tsx; supabase/tests/password_link.sql
A68: ADM-006 | B68: Portal de administración | C68: Rutas antiguas | D68: Las direcciones antiguas redirigen a su equivalente actual | E68: Regresión | F68: Media | G68: ADMIN | H68: Sesión iniciada como ADMIN. | I68: 1. Abrir /admin/usuarios en la app 2. Abrir /o/{slug}/equipos 3. Abrir /o/{slug}/facturacion 4. Abrir /cocinas 5. Abrir /invitacion/abc123 | K68: /admin/* → /app (cuenta por defecto). /o/{slug}/equipos → /k/{cuenta}/users. /o/{slug}/facturacion → /k/{cuenta}/settings/billing. /cocinas → /cuentas. /invitacion/:token → /login. No aparece ninguna pantalla en blanco. | L68: Pendiente | Q68: src/app/routes.tsx; src/app/legacyOrgRoutes.ts; ADR 0024 (sección 3)
A69: ADM-007 | B69: Portal de administración | C69: /signup-admin | D69: El registro en /signup-admin exige 8 caracteres y no otorga rol de plataforma | E69: Seguridad | F69: Media | G69: Sin sesión | H69: Ruta /signup-admin disponible. | I69: 1. Abrir /signup-admin 2. Intentar registrarse con una contraseña de 6 caracteres 3. Registrarse con datos válidos y revisar el rol obtenido | J69: admin.prueba@negocio.co; contraseña de 6 y de 8 caracteres | K69: Se pide mínimo 8 caracteres como en el resto de la app, y la cuenta creada no queda como SUPERADMIN de plataforma (la base rechaza el valor enviado desde el navegador). | L69: Pendiente | Q69: src/modules/auth/pages/SignUpAdminPage.tsx
A70: INI-001 | B70: Inicio | C70: Encabezado de Inicio | D70: Inicio muestra saludo, fecha, reloj y «Ventas de hoy» con el número de pedidos | E70: Funcional | F70: Alta | G70: ADMIN | H70: Cuenta de prueba «Cocina Demo QA» con 3 pedidos no cancelados hoy por $25.000, $18.000 y $7.000. Sesión iniciada como ADMIN «Laura Pruebas». | I70: 1. Entrar a /k/cocina-demo-qa/dashboard 2. Revisar el encabezado «Inicio» 3. Esperar 3 segundos observando el reloj | J70: Pedidos de hoy: $25.000 + $18.000 + $7.000 | K70: Se ve «Hola, Laura», la fecha larga de hoy y un reloj HH:MM:SS que avanza cada segundo; «Ventas de hoy» muestra $50.000 con «3 pedidos»; a la derecha los accesos «Compras», «Clientes» e «Insights». | L70: Pendiente | Q70: src/modules/dashboard/pages/DashboardPage.tsx; content/help/intro/home-screen.md
A71: INI-002 | B71: Inicio | C71: Ocultar ventas de hoy | D71: El ojo de «Ventas de hoy» oculta y vuelve a mostrar la cifra | E71: UI/UX | F71: Media | G71: ADMIN, GERENTE | H71: Hay ventas registradas hoy. | I71: 1. Abrir Inicio 2. Tocar «Ventas de hoy» (icono de ojo) 3. Volver a tocarlo 4. Ocultar de nuevo y recargar la página | K71: Al tocar, la cifra cambia a «••••••» y el icono pasa a ojo tachado; al tocar otra vez vuelve el monto. Tras recargar, la cifra se muestra de nuevo (el ocultamiento no se guarda). | L71: Pendiente | Q71: src/modules/dashboard/pages/DashboardPage.tsx; content/help/intro/home-screen.md
A72: INI-003 | B72: Inicio | C72: Necesita atención | D72: Sin pendientes, «Necesita atención» dice «Todo al día: nada pendiente por ahora.» | E72: Funcional | F72: Media | G72: ADMIN | H72: Cuenta sin pedidos atrasados ni por confirmar, sin insumos bajo el mínimo y sin clientes con saldo vencido. | I72: 1. Abrir Inicio 2. Revisar el bloque «Necesita atención» | K72: Se muestra el aviso verde «Todo al día: nada pendiente por ahora.» y ninguna tarjeta. | L72: Pendiente | Q72: src/modules/dashboard/pages/DashboardPage.tsx; content/help/intro/home-screen.md; docs/adr/0037
A73: INI-004 | B73: Inicio | C73: Necesita atención | D73: Las tarjetas de «Necesita atención» muestran la cifra, resaltan lo urgente y abren la lista filtrada | E73: Funcional | F73: Alta | G73: ADMIN | H73: 2 pedidos fuera de SLA (atrasados) y 1 insumo «Pollo QA» bajo el mínimo. | I73: 1. Abrir Inicio 2. Ubicar la tarjeta de pedidos atrasados 3. Tocarla 4. Volver a Inicio y tocar la tarjeta de insumos bajo el mínimo | J73: Insumo: Pollo QA (mínimo 5 kg, stock 2 kg) | K73: La tarjeta de atrasados muestra «2» con borde ámbar (urgente); al tocarla abre la lista de pedidos ya filtrada; la de insumos abre Abastecimiento filtrado. Lo no urgente tiene borde neutro. | L73: Pendiente | Q73: src/modules/dashboard/pages/DashboardPage.tsx; content/help/intro/home-screen.md
A74: INI-005 | B74: Inicio | C74: Actualización de cifras | D74: «Ventas de hoy» se actualiza sin recargar tras crear un pedido | E74: Integración | F74: Alta | G74: CAJA | H74: Inicio abierto en una pestaña con «Ventas de hoy» = $50.000 (3 pedidos). | I74: 1. En otra vista de la misma pestaña, crear un pedido de $12.000 2. Volver a Inicio sin recargar 3. Si no cambió, esperar hasta 60 s | J74: Pedido nuevo: 1 Sopa QA $12.000 | K74: «Ventas de hoy» pasa a $62.000 y «4 pedidos» tras la acción (se invalida el resumen) o, como máximo, en el refresco de cada minuto. | L74: Pendiente | Q74: src/shared/lib/queryClient.ts; src/modules/dashboard/hooks/useDashboard.ts
A75: INI-006 | B75: Inicio | C75: Inicio por rol | D75: COCINA y DOMICILIARIO no tienen Inicio: la URL directa los lleva a su pantalla | E75: Permisos | F75: Alta | G75: COCINA, DOMICILIARIO | H75: Usuarios de prueba cocina.qa@prueba.test y domi.qa@prueba.test con esos roles en «Cocina Demo QA». | I75: 1. Iniciar sesión como COCINA 2. Escribir en la barra /k/cocina-demo-qa/dashboard 3. Repetir con DOMICILIARIO | K75: No se muestra Inicio ni sus cifras: COCINA es redirigido a Operación → Cocina y DOMICILIARIO a Operación → Despacho; Inicio no aparece en su menú. | L75: Pendiente | Q75: src/app/AppLayout.tsx (isSectionAllowed/homeSection); content/help/intro/roles.md
A76: INI-007 | B76: Inicio | C76: Tarjetas por permiso | D76: INVENTARIO ve Inicio sin «Pedidos recientes» ni la cartera de clientes | E76: Permisos | F76: Media | G76: INVENTARIO | H76: Usuario inventario.qa@prueba.test con rol INVENTARIO. | I76: 1. Iniciar sesión como INVENTARIO 2. Abrir Inicio 3. Revisar las tarjetas inferiores | K76: No aparece «Pedidos recientes» (requiere despachar); «Cartera y compras» muestra solo «Compras del mes» y «Mermas del mes», sin «Por cobrar» ni «Vencido»; «En turno ahora» solo si el rol tiene ver personal. | L76: Pendiente | Q76: src/modules/dashboard/pages/DashboardPage.tsx; content/help/intro/home-screen.md
A77: INI-008 | B77: Inicio | C77: Accesos rápidos | D77: Un acceso rápido a un módulo sin permiso no muestra datos del módulo | E77: Permisos | F77: Media | G77: CAJA | H77: Rol CAJA sin permisos de abastecimiento. | I77: 1. Iniciar sesión como CAJA y abrir Inicio 2. Tocar el acceso rápido «Compras» | K77: No se muestran compras: la app redirige a la pantalla de inicio del rol (Operación → Tablero). Observación: el acceso «Compras» se muestra aunque el rol no lo pueda abrir (revisar si debería ocultarse). | L77: Pendiente | Q77: src/modules/dashboard/pages/DashboardPage.tsx (HeroAction); src/app/AppLayout.tsx
A78: NOT-001 | B78: Notificaciones | C78: Campana | D78: La campana cuenta las no leídas y muestra 9+ | E78: Funcional | F78: Alta | G78: ADMIN | H78: La cuenta tiene más de 9 avisos sin leer para el usuario. | I78: 1. Ubicar la campana sobre el avatar (escritorio) o junto al avatar (celular) 2. Pasar el cursor sobre ella | K78: El globito muestra «9+» y el tooltip/etiqueta dice «Notificaciones: N sin leer»; sin avisos sin leer no hay globito. | L78: Pendiente | Q78: src/modules/notifications/components/NotificationBell.tsx; src/modules/notifications/lib.ts; content/help/intro/notifications.md
A79: NOT-002 | B79: Notificaciones | C79: Campana | D79: Abrir un aviso navega a su pantalla y lo marca como leído | E79: Funcional | F79: Alta | G79: CAJA | H79: Hay 2 pedidos «Por confirmar» y el aviso no se ha leído. | I79: 1. Abrir la campana 2. Tocar «2 pedidos por confirmar» («Ver pedidos») | K79: El panel se cierra y se abre Operación → «Lista» filtrada por «Por confirmar» con rango «Todo»; al volver a abrir la campana el aviso aparece leído (sin punto naranja) y el contador bajó en 1. | L79: Pendiente | Q79: src/modules/notifications/components/NotificationBell.tsx; supabase/tests/notifications.sql (Operation)
A80: NOT-003 | B80: Notificaciones | C80: Campana | D80: Pestañas «Todas» e «IA» y estado vacío | E80: Funcional | F80: Media | G80: ADMIN | H80: Hay avisos de operación y sugerencias de IA. | I80: 1. Abrir la campana 2. Tocar «IA» 3. Marcar todo como leído en «IA» y revisar «Todas» | K80: «IA» muestra solo las sugerencias con la etiqueta ✨ IA y su fuente (p. ej. «Sugerencias de Cocina en vivo»); cada pestaña muestra su conteo de no leídas; sin avisos se muestra «Todo al día» o «Sin sugerencias de IA por ahora». | L80: Pendiente | Q80: src/modules/notifications/components/NotificationBell.tsx; supabase/tests/notifications.sql (AI)
A81: NOT-004 | B81: Notificaciones | C81: Campana | D81: «Marcar todo como leído» es personal y sigue al usuario | E81: Funcional | F81: Media | G81: ADMIN, CAJA | H81: ADMIN y CAJA tienen el mismo aviso de pedidos por confirmar sin leer. | I81: 1. Como ADMIN, tocar «Marcar todo como leído» 2. Abrir la app como ADMIN en otro navegador 3. Iniciar sesión como CAJA y abrir la campana | K81: Para ADMIN el contador queda en 0 también en el otro navegador; para CAJA el aviso sigue sin leer. | L81: Pendiente | Q81: supabase/tests/notifications.sql (Read); docs/adr/0037-centro-de-notificaciones.md
A82: NOT-005 | B82: Notificaciones | C82: Permisos de avisos | D82: Cada rol recibe solo los avisos de sus pantallas | E82: Permisos | F82: Alta | G82: CAJA, INVENTARIO, ADMIN | H82: Hay pedidos por confirmar, insumos bajo el mínimo y un análisis de IA con error. | I82: 1. Abrir la campana como ADMIN 2. Abrirla como CAJA 3. Abrirla como INVENTARIO | K82: ADMIN ve todo, incluido el análisis de IA con error; CAJA ve los pedidos por confirmar pero no los insumos bajo el mínimo, ni errores de IA, ni avisos del plan; INVENTARIO ve los insumos bajo el mínimo pero no los pedidos por confirmar. | L82: Pendiente | Q82: supabase/tests/notifications.sql (Roles); supabase/migrations/20261006180000_dk_notifications.sql
A83: NOT-006 | B83: Notificaciones | C83: Inicio | D83: «Necesita atención» muestra tarjetas que abren la lista filtrada | E83: Funcional | F83: Alta | G83: ADMIN | H83: Hay pedidos atrasados y pedidos por confirmar. | I83: 1. Abrir «Inicio» 2. Revisar el bloque «Necesita atención» 3. Tocar la tarjeta de pedidos por confirmar | K83: Cada tarjeta muestra la cifra grande y la etiqueta; la de pedidos atrasados tiene borde ámbar; los avisos no se repiten; la tarjeta abre la Lista ya filtrada. | L83: Pendiente | Q83: src/modules/dashboard/pages/DashboardPage.tsx (NeedsAttention); content/help/intro/home-screen.md; docs/adr/0037-centro-de-notificaciones.md
A84: NOT-007 | B84: Notificaciones | C84: Inicio | D84: Sin pendientes Inicio dice «Todo al día» y la línea de IA abre la campana | E84: UI/UX | F84: Media | G84: ADMIN | H84: No hay pedidos atrasados ni por confirmar ni insumos bajo el mínimo; hay 2 sugerencias de IA sin leer. | I84: 1. Abrir «Inicio» 2. Tocar «✨ 2 sugerencias de IA nuevas · Ver en notificaciones» | K84: El bloque dice «Todo al día: nada pendiente por ahora.»; la línea de IA abre el panel de la campana. | L84: Pendiente | Q84: src/modules/dashboard/pages/DashboardPage.tsx; content/help/intro/home-screen.md
A85: NOT-008 | B85: Notificaciones | C85: Accesibilidad | D85: Campana operable con teclado y lectores de pantalla | E85: Accesibilidad | F85: Baja | G85: CAJA | H85: Hay avisos sin leer. | I85: 1. Llegar a la campana con Tab y presionar Enter 2. Moverse a las pestañas «Todas»/«IA» y activarlas con Enter 3. Recorrer los avisos con Tab y abrir uno con Enter | K85: La campana anuncia «Notificaciones: N sin leer»; las pestañas exponen su estado seleccionado; los avisos sin leer tienen la etiqueta «Sin leer»; todo se puede usar sin mouse. | L85: Pendiente | Q85: src/modules/notifications/components/NotificationBell.tsx
A86: PED-001 | B86: Pedidos | C86: Crear pedido | D86: Crear un pedido en borrador para un cliente existente | E86: Funcional | F86: Alta | G86: CAJA | H86: Sesión iniciada como CAJA. Existe el cliente «Laura Gómez» con teléfono +57 300 123 4567. | I86: 1. Ir a Operación (vista «Tablero») 2. Tocar «Nuevo pedido» 3. En «Cliente» escribir «Laura» y elegir «Laura Gómez» 4. Tocar «Crear pedido» | J86: Cliente: Laura Gómez | K86: El panel cambia a «Nuevo pedido #N» con el subtítulo «Cliente: Laura Gómez · agrega los platos y confírmalo» y el pedido aparece de inmediato en la columna «Por confirmar» del tablero. | L86: Pendiente | Q86: src/modules/orders/components/NewOrderDrawer.tsx; content/help/orders/create-order.md
A87: PED-002 | B87: Pedidos | C87: Crear pedido | D87: Crear el cliente al vuelo desde el selector y que el pedido se cree solo | E87: Funcional | F87: Alta | G87: CAJA | H87: No existe ningún cliente llamado «Andrés Rojas». | I87: 1. Tocar «Nuevo pedido» 2. En «Cliente» escribir «Andrés Rojas» 3. Tocar la opción «Crear "Andrés Rojas"» 4. Verificar que el modal «Nuevo cliente» trae el «Nombre» prellenado 5. Completar «Teléfono» 310 555 1234 y tocar «Crear cliente» | J87: Nombre: Andrés Rojas; Teléfono: +57 310 555 1234 | K87: Aparece el aviso «Cliente "Andrés Rojas" creado.», el modal se cierra y el borrador se crea automáticamente («Nuevo pedido #N», cliente Andrés Rojas) sin tocar «Crear pedido». | L87: Pendiente | Q87: src/modules/orders/components/NewOrderDrawer.tsx; src/modules/customers/components/CreateCustomerModal.tsx; content/help/orders/create-order.md
A88: PED-003 | B88: Pedidos | C88: Crear pedido | D88: Atajo de teclado N abre «Nuevo pedido» y no interfiere al escribir | E88: UI/UX | F88: Media | G88: CAJA | H88: Operación abierta en la vista «Tablero» o «Lista». | I88: 1. Con el foco fuera de cualquier campo, presionar la tecla N 2. Cerrar el panel 3. Ir a la vista «Lista» y escribir «Nicolás» en el buscador | J88: Texto: Nicolás | K88: La tecla N abre el panel «Nuevo pedido»; al escribir una «N» dentro del buscador no se abre el panel y el texto se escribe normalmente. | L88: Pendiente | Q88: src/modules/operations/pages/OperationsPage.tsx (isTyping); content/help/orders/operations-center.md
A89: PED-004 | B89: Pedidos | C89: Agregar platos | D89: Agregar un plato con precio del catálogo y ver el total en COP | E89: Funcional | F89: Alta | G89: CAJA | H89: Borrador «Por confirmar» abierto. Existe el plato activo «Hamburguesa clásica» a $25.000. | I89: 1. En «Plato» buscar y elegir «Hamburguesa clásica» 2. Verificar que «Precio unitario» se llena con 25.000 3. Ajustar «Cantidad» a 2 4. Tocar «Agregar plato» | J89: Plato: Hamburguesa clásica; Cantidad: 2; Precio: $25.000 | K89: La tabla muestra la fila con Cantidad 2, «Precio unit.» $25.000 y Total $50.000; el pie muestra «Subtotal», «Descuento», «Domicilio» y «Total» con el código COP (p. ej. «$50.000 COP» si no hay domicilio ni descuento). El formulario se limpia (Cantidad vuelve a 1). | L89: Pendiente | Q89: src/modules/orders/components/OrderBuilder.tsx; docs/adr/0039-moneda-telefonos-correos-y-formularios.md (D1)
A90: PED-005 | B90: Pedidos | C90: Observaciones | D90: Usar las sugerencias rápidas de observación | E90: Funcional | F90: Media | G90: CAJA | H90: Borrador «Por confirmar» abierto. | I90: 1. Elegir un plato 2. Tocar la sugerencia «Sin cebolla» 3. Verificar que el campo «Observación» dice «Sin cebolla» 4. Tocar de nuevo «Sin cebolla» y verificar que el campo se vacía 5. Tocar «Para llevar» y luego «Agregar plato» | J90: Sugerencias: «Sin cebolla», «Sin tomate», «Sin picante», «Extra queso», «Para llevar» | K90: La sugerencia activa llena el campo y al tocarla otra vez se quita; la línea agregada muestra «Para llevar» en la columna «Observación» y, tras confirmar, la observación se ve en ámbar en el detalle del pedido. | L90: Pendiente | Q90: src/modules/orders/components/OrderBuilder.tsx (OBSERVATION_SUGGESTIONS); src/modules/orders/components/OrderDetailDrawer.tsx
A91: PED-006 | B91: Pedidos | C91: Agregar platos | D91: El «Precio unitario» solo acepta pesos positivos con separador de miles | E91: Validación | F91: Media | G91: CAJA | H91: Borrador abierto con un plato elegido. | I91: 1. Borrar el «Precio unitario» 2. Escribir «-1500abc» 3. Escribir 1250000 4. Salir del campo | J91: Entradas: -1500abc; 1250000 | K91: Se descartan el signo menos y las letras (queda 1.500); al escribir 1250000 el campo muestra «1.250.000» con el prefijo $ y el sufijo COP. | L91: Pendiente | Q91: src/shared/ui/CurrencyInput.tsx; src/shared/utils/numberInput.ts; docs/adr/0039-moneda-telefonos-correos-y-formularios.md (D2)
A92: PED-007 | B92: Pedidos | C92: Confirmar pedido | D92: Un pedido sin platos no se puede confirmar | E92: Negativo | F92: Alta | G92: CAJA | H92: Borrador recién creado, sin platos. | I92: 1. Abrir el borrador 2. Observar «Confirmar pedido» y el estado vacío de la tabla 3. En el tablero, observar la tarjeta del pedido | K92: La tabla muestra «Sin platos todavía» / «Agrega el primer plato con el formulario de arriba.»; «Confirmar pedido» está deshabilitado y la tarjeta muestra «Sin platos todavía» con el botón de confirmar deshabilitado. | L92: Pendiente | Q92: src/modules/orders/components/OrderBuilder.tsx; src/modules/orders/board/useOrderActions.ts (primaryDisabled)
A93: PED-008 | B93: Pedidos | C93: Confirmar pedido | D93: Plato sin receta activa: la confirmación se rechaza | E93: Negativo | F93: Alta | G93: CAJA | H93: Existe el plato activo «Ensalada César» sin receta activa. Borrador con ese plato. | I93: 1. Abrir el borrador 2. Tocar «Confirmar» (tarjeta) o «Confirmar pedido» 3. Tocar «Sí, confirmar» | J93: Plato: Ensalada César (sin receta) | K93: Aparece un aviso de error con el mensaje de la base (contiene «no tiene una receta activa; no se puede confirmar el pedido»); el pedido sigue en «Por confirmar» y no se reserva ningún insumo. | L93: Pendiente | Q93: supabase/migrations/20260912232725_dk_orders_schema.sql (dk_confirm_order); content/help/orders/confirm-cancel.md
A94: PED-009 | B94: Pedidos | C94: Confirmar pedido | D94: Stock insuficiente: la confirmación se rechaza completa | E94: Negativo | F94: Alta | G94: CAJA | H94: Borrador con 10 «Hamburguesa clásica»; el stock disponible de pan solo alcanza para 5. | I94: 1. Abrir el borrador 2. Tocar «Confirmar pedido» → «Sí, confirmar» 3. Revisar el stock disponible del insumo en Abastecimiento | J94: Cantidad: 10 hamburguesas; stock para 5 | K94: Aviso de error que empieza por «Stock insuficiente para el insumo…» con disponible y requerido; el pedido sigue «Por confirmar» y no hay reservas parciales (el stock disponible no cambia). | L94: Pendiente | Q94: supabase/migrations/20260912232725_dk_orders_schema.sql; docs/03-order-lifecycle.md
A95: PED-010 | B95: Pedidos | C95: Confirmar pedido | D95: Confirmar un pedido con platos y stock suficiente | E95: Funcional | F95: Alta | G95: CAJA | H95: Borrador de «Laura Gómez» con 2 platos con receta activa y stock suficiente. | I95: 1. Tocar «Confirmar» en la tarjeta de «Por confirmar» 2. Leer el diálogo «Confirmar pedido #N» 3. Tocar «Sí, confirmar» | J95: Cliente: Laura Gómez; 2 platos | K95: El diálogo indica que se reserva el inventario para los 2 plato(s) de Laura Gómez con el total; al confirmar aparece «Pedido #N confirmado y enviado a cocina.» y la tarjeta pasa a «En cola». | L95: Pendiente | Q95: src/modules/orders/board/BoardDialogs.tsx (ConfirmOrderDialog); content/help/orders/confirm-cancel.md
A96: PED-011 | B96: Pedidos | C96: Confirmar pedido | D96: Pedido confirmado llega a Cocina y reserva insumos | E96: Integración | F96: Alta | G96: CAJA, COCINA | H96: Pedido recién confirmado por CAJA. | I96: 1. Como COCINA, abrir Operación (empieza en la vista «Cocina») 2. Buscar el pedido en la columna «En cola» 3. Abrir el pedido y revisar la tarjeta «Insumos» | K96: El pedido aparece en «En cola» de la vista «Cocina» (a más tardar en el siguiente refresco) con sus platos y observaciones; «Insumos» lista los insumos de la receta con estado «Reservado». | L96: Pendiente | Q96: docs/adr/0031-centro-de-operaciones.md; src/modules/orders/components/OrderDetailDrawer.tsx (StockCard); docs/03-order-lifecycle.md
A97: PED-012 | B97: Pedidos | C97: Confirmar pedido | D97: Tras confirmar ya no se pueden agregar ni quitar platos | E97: Negativo | F97: Alta | G97: CAJA | H97: Pedido en estado «En cola». | I97: 1. Abrir el detalle del pedido 2. Buscar el formulario «Agregar plato» y el botón «Quitar» | K97: El formulario para agregar platos no aparece y la tabla no tiene la columna de acciones «Quitar»; los platos solo se ven. | L97: Pendiente | Q97: src/modules/orders/components/OrderBuilder.tsx (canEditItems = NUEVO && orders.edit); content/help/orders/create-order.md
A98: PED-013 | B98: Pedidos | C98: Cancelar pedido | D98: Cancelar un pedido en cola con motivo libera la reserva | E98: Funcional | F98: Alta | G98: CAJA | H98: Pedido en «En cola» con insumos «Reservado». | I98: 1. Abrir el pedido y tocar «Cancelar pedido» 2. En «Motivo (opcional)» escribir «El cliente se arrepintió» 3. Tocar «Sí, cancelar» 4. Ir a «Lista» y filtrar «Cancelados» 5. Abrir el pedido | J98: Motivo: El cliente se arrepintió | K98: Aviso «Pedido #N cancelado.»; el pedido sale del tablero y aparece en «Cancelados»; los insumos quedan «Liberado» y la «Línea de tiempo» muestra la transición a «Cancelado» con el motivo y el usuario. | L98: Pendiente | Q98: src/modules/orders/board/BoardDialogs.tsx (CancelOrderDialog); docs/03-order-lifecycle.md; content/help/orders/confirm-cancel.md
A99: PED-014 | B99: Pedidos | C99: Cancelar pedido | D99: Cancelación tardía con un plato ya listo marca «revisar devolución» | E99: Funcional | F99: Alta | G99: ADMIN | H99: Pedido en «Preparando» con un plato ya en «Listo» (insumos consumidos). | I99: 1. Abrir el pedido 2. Tocar «Cancelar pedido» → «Sí, cancelar» 3. Volver a abrir el pedido desde «Lista» → «Cancelados» | K99: El pedido queda «Cancelado» con la insignia «revisar devolución»; en inventario se registra una DEVOLUCION por lo consumido. | L99: Pendiente | Q99: supabase/migrations/20260915230656_dk_kitchen_revert_cancel_sla_settings.sql (dk_cancel_order); src/modules/orders/components/OrderDetailDrawer.tsx
A100: PED-015 | B100: Pedidos | C100: Prioridad | D100: Marcar y quitar «Prioritario» en un pedido de cocina | E100: Funcional | F100: Media | G100: COCINA | H100: Dos pedidos en «En cola»; el más reciente es el de «Carlos Méndez». | I100: 1. Abrir el pedido de Carlos Méndez 2. Tocar «Prioritario» 3. Volver al tablero de Cocina 4. Abrir el pedido y tocar «Quitar prioridad» | J100: Cliente: Carlos Méndez | K100: La tarjeta muestra la bandera (borde violeta) y sube al primer lugar de su columna; al tocar «Quitar prioridad» vuelve al orden por hora de creación. | L100: Pendiente | Q100: src/modules/orders/board/useOrderActions.ts; src/modules/operations/pages/OperationsPage.tsx (orden por prioridad); content/help/orders/order-states.md
...

Sheet Posibles defectos
A1: # | B1: Severidad | C1: Módulo | D1: Descripción | E1: Dónde (código) | F1: Casos relacionados | G1: Estado | H1: Notas
A2: 1 | B2: Alta | C2: Cocina | D2: Si un plato vuelve de «Listo» a un estado anterior y luego otra vez a «Listo», el inventario no se descuenta de nuevo; si después se cancela, el stock se devuelve dos veces. | E2: supabase/migrations/20260915230656_dk_kitchen_revert_cancel_sla_settings.sql, 20260912233856_dk_kitchen_workflow.sql | F2: COC-006, COC-007, PED-014 | G2: Por confirmar
A3: 2 | B3: Alta | C3: Clientes | D3: Editar un cliente desde el menú ⋯ de la lista borra su correo (el formulario abre sin él y guarda vacío). Desde la ficha del cliente funciona bien. | E3: src/modules/customers/components/CustomerActions.tsx | F3: CLI-021 | G3: Por confirmar
A4: 3 | B4: Alta | C4: Copilot | D4: La conversación guardada de Copilot depende solo de la cuenta: al cambiar de rol o de usuario en la misma pestaña (30 min) puede verse y enviarse lo que respondió al rol anterior. Cerrar sesión no la borra. | E4: src/modules/copilot/lib/conversation.ts | F4: COP-011, TRV-013 | G4: Por confirmar
A5: 4 | B5: Alta | C5: Insights | D5: El CSV exportado no neutraliza celdas que empiezan por =, +, - o @: un plato llamado «=HYPERLINK(...)» se ejecuta como fórmula en Excel. | E5: src/modules/insights/lib/csv.ts | F5: INS-014 | G5: Por confirmar
A6: 5 | B6: Alta | C6: Catálogo y menú | D6: COCINA ve los controles del planificador (arrastrar, +, ×, reglas) pero la base solo le deja cambiar el día de hoy: agregar falla con error de seguridad y editar otro día puede mostrar éxito sin guardar. | E6: src/modules/menuPlanner | F6: CAT-020 | G6: Por confirmar
A7: 6 | B7: Alta | C7: Catálogo y menú | D7: Las reglas del día (precio promocional, agotado, horario, límite de unidades) no se aplican al crear pedidos a mano; el límite y el horario no se aplican en ningún lado. | E7: src/modules/orders, src/modules/menuPlanner | F7: CAT-016 | G7: Por confirmar
A8: 7 | B8: Alta | C8: Transversal | D8: Pegar un monto con punto decimal en un campo de dinero («85000.50») se convierte en 8.500.050. | E8: src/shared/components (CurrencyInput), src/shared/utils/numberInput.ts | F8: TRV-014 | G8: Por confirmar
A9: 8 | B9: Media | C9: Acceso y cuenta | D9: El inicio de sesión de la app muestra el error de Supabase en inglés («Invalid login credentials»); el portal de administración sí lo traduce. | E9: src/modules/auth/pages/LoginPage.tsx, src/shared/hooks/useAuth.tsx | F9: ACC-007 | G9: Por confirmar
A10: 9 | B10: Media | C10: Pedidos / Abastecimiento | D10: Algunos errores muestran el ID interno en lugar del nombre: «El plato <id> no tiene una receta activa», «Stock insuficiente para el insumo <id>», «No hay conversion definida…». | E10: supabase/migrations (dk_confirm_order, reservas) | F10: PED-008, PED-009, ABA-009 | G10: Por confirmar
A11: 10 | B11: Media | C11: Varios | D11: Errores técnicos llegan crudos a la pantalla: «PENDING_INVITATION: …» al registrarse, «Hasta» antes de «Desde», máximo menor que mínimo, código de insumo duplicado, línea de compra con cantidad 0. | E11: src/shared/utils (getErrorMessage) | F11: ACC-018, CAT-013, ABA-003 | G11: Por confirmar
A12: 11 | B12: Media | C12: Pagos y cartera | D12: «Vencido» nunca se activa: dk_orders.due_date no se llena, así que el filtro «Vencidos», «Saldo vencido» y el aviso de cliente moroso siempre dan cero. | E12: docs/adr/0031-centro-de-operaciones.md | F12: PAG-016 | G12: Por confirmar
A13: 12 | B13: Media | C13: Clientes | D13: Se puede registrar una queja ya «Resuelta» sin «Respuesta o solución»; al cerrarla desde el seguimiento sí se exige. | E13: src/modules/customers/components/profile | F13: CLI-024, CLI-017 | G13: Por confirmar
... A30: 29 | B30: Baja | C30: Centro de ayuda | D30: Desajustes de la ayuda con el código: el artículo de Insights no incluye a CAJA en su audiencia, y «Facturación» solo la ve el dueño (SUPER_ADMIN), no un ADMIN invitado. | E30: content/help/reports/insights.md, content/help/settings/settings.md | F30: CFG-003, INS-006 | G30: Por confirmar
